<metadata xml:lang="en"><Esri><CreaDate>20110121</CreaDate><CreaTime>16274900</CreaTime><SyncOnce>FALSE</SyncOnce><SyncDate>20231114</SyncDate><SyncTime>00542200</SyncTime><ModDate>20231114</ModDate><ModTime>00542200</ModTime><DataProperties><itemProps><itemName Sync="TRUE">TRAINS_RTE_TRAIN</itemName><imsContentType Sync="TRUE" export="False">002</imsContentType><itemLocation><linkage Sync="TRUE">file://\\TSSARCGIS-WAP11\E$\MassGIS\Data_Distribution_Files\statewide_viewer_SHP\gisdata\men1\infrastructure\TRAINS_RTE_TRAIN.shp</linkage><protocol Sync="TRUE">Local Area Network</protocol></itemLocation><nativeExtBox><westBL Sync="TRUE">171357.015600</westBL><eastBL Sync="TRUE">303484.250000</eastBL><southBL Sync="TRUE">803658.050700</southBL><northBL Sync="TRUE">954339.062500</northBL><exTypeCode Sync="TRUE">1</exTypeCode></nativeExtBox><itemSize Sync="TRUE">0.000</itemSize></itemProps><coordRef><type Sync="TRUE">Projected</type><geogcsn Sync="TRUE">GCS_North_American_1983</geogcsn><projcsn Sync="TRUE">NAD_1983_StatePlane_Massachusetts_Mainland_FIPS_2001</projcsn><peXml Sync="TRUE">&lt;ProjectedCoordinateSystem xsi:type='typens:ProjectedCoordinateSystem' xmlns:xsi='http://www.w3.org/2001/XMLSchema-instance' xmlns:xs='http://www.w3.org/2001/XMLSchema' xmlns:typens='http://www.esri.com/schemas/ArcGIS/10.8'&gt;&lt;WKT&gt;PROJCS[&amp;quot;NAD_1983_StatePlane_Massachusetts_Mainland_FIPS_2001&amp;quot;,GEOGCS[&amp;quot;GCS_North_American_1983&amp;quot;,DATUM[&amp;quot;D_North_American_1983&amp;quot;,SPHEROID[&amp;quot;GRS_1980&amp;quot;,6378137.0,298.257222101]],PRIMEM[&amp;quot;Greenwich&amp;quot;,0.0],UNIT[&amp;quot;Degree&amp;quot;,0.0174532925199433]],PROJECTION[&amp;quot;Lambert_Conformal_Conic&amp;quot;],PARAMETER[&amp;quot;False_Easting&amp;quot;,200000.0],PARAMETER[&amp;quot;False_Northing&amp;quot;,750000.0],PARAMETER[&amp;quot;Central_Meridian&amp;quot;,-71.5],PARAMETER[&amp;quot;Standard_Parallel_1&amp;quot;,41.71666666666667],PARAMETER[&amp;quot;Standard_Parallel_2&amp;quot;,42.68333333333333],PARAMETER[&amp;quot;Latitude_Of_Origin&amp;quot;,41.0],UNIT[&amp;quot;Meter&amp;quot;,1.0],AUTHORITY[&amp;quot;EPSG&amp;quot;,26986]]&lt;/WKT&gt;&lt;XOrigin&gt;-36530900&lt;/XOrigin&gt;&lt;YOrigin&gt;-28803200&lt;/YOrigin&gt;&lt;XYScale&gt;122610652.81195112&lt;/XYScale&gt;&lt;ZOrigin&gt;-100000&lt;/ZOrigin&gt;&lt;ZScale&gt;10000&lt;/ZScale&gt;&lt;MOrigin&gt;-100000&lt;/MOrigin&gt;&lt;MScale&gt;10000&lt;/MScale&gt;&lt;XYTolerance&gt;0.001&lt;/XYTolerance&gt;&lt;ZTolerance&gt;0.001&lt;/ZTolerance&gt;&lt;MTolerance&gt;0.001&lt;/MTolerance&gt;&lt;HighPrecision&gt;true&lt;/HighPrecision&gt;&lt;WKID&gt;26986&lt;/WKID&gt;&lt;LatestWKID&gt;26986&lt;/LatestWKID&gt;&lt;/ProjectedCoordinateSystem&gt;</peXml><csUnits Sync="TRUE">Linear Unit: Meter (1.000000)</csUnits></coordRef><lineage><Process ToolSource="c:\program files (x86)\arcgis\desktop10.8\ArcToolbox\Toolboxes\Data Management Tools.tbx\CopyFeatures" Date="20231114" Time="005422">CopyFeatures "Database Connections\AWS_VTP_PROD_GISDATA.sde\GISDATA.TRAINS_RTE_TRAIN" E:\MassGIS\Data_Distribution_Files\statewide_viewer_SHP\gisdata\men1\infrastructure\TRAINS_RTE_TRAIN.shp # 0 0 0</Process></lineage></DataProperties><ArcGISFormat>1.0</ArcGISFormat><scaleRange><minScale>625000</minScale><maxScale>5000</maxScale></scaleRange><ArcGISProfile>FGDC</ArcGISProfile></Esri><idinfo><citation><citeinfo><ftname Sync="TRUE">GISDATA.TRAINS_RTE_TRAIN2</ftname></citeinfo></citation><spdom><bounding><westbc Sync="TRUE">-71.982968</westbc><eastbc Sync="TRUE">-70.234306</eastbc><northbc Sync="TRUE">42.839668</northbc><southbc Sync="TRUE">41.638204</southbc></bounding><lboundng><leftbc Sync="TRUE">160514.578112</leftbc><rightbc Sync="TRUE">303484.250002</rightbc><bottombc Sync="TRUE">821638.624999</bottombc><topbc Sync="TRUE">954339.062501</topbc></lboundng></spdom></idinfo><dataIdInfo><envirDesc Sync="TRUE"> Version 6.2 (Build 9200) ; Esri ArcGIS 10.9.1.28388</envirDesc><dataLang><languageCode Sync="FALSE" value="eng" country="US"/><countryCode value="USA" Sync="TRUE"/></dataLang><idCitation xmlns=""><resTitle Sync="FALSE">MBTA Commuter Rail Routes</resTitle><presForm xmlns=""><PresFormCd Sync="TRUE" value="005"/></presForm><date><reviseDate>2021-12-23T00:00:00</reviseDate><pubDate>2014-07-15T00:00:00</pubDate></date><citRespParty xmlns=""><rpOrgName>Central Transportatin Planning Staff</rpOrgName><role><RoleCd value="006"/></role></citRespParty></idCitation><spatRpType><SpatRepTypCd Sync="TRUE" value="001"/></spatRpType><dataExt xmlns=""><geoEle><GeoBndBox esriExtentType="native"><westBL Sync="TRUE">160514.578112</westBL><eastBL Sync="TRUE">303484.250002</eastBL><northBL Sync="TRUE">954339.062501</northBL><southBL Sync="TRUE">821638.624999</southBL><exTypeCode Sync="TRUE">1</exTypeCode></GeoBndBox></geoEle></dataExt><geoBox esriExtentType="decdegrees"><westBL Sync="TRUE">-71.982968</westBL><eastBL Sync="TRUE">-70.234306</eastBL><northBL Sync="TRUE">42.839668</northBL><southBL Sync="TRUE">41.638204</southBL><exTypeCode Sync="TRUE">1</exTypeCode></geoBox><descKeys><thesaName uuidref="723f6998-058e-11dc-8314-0800200c9a66"/><keyword Sync="TRUE">002</keyword></descKeys><idPurp>Planning and analysis</idPurp><idAbs>&lt;DIV STYLE="text-align:Left;"&gt;&lt;DIV&gt;&lt;DIV&gt;&lt;P&gt;&lt;SPAN&gt;This layer is a subset of the full Trains (TRAINS_ARC) dataset. It contains one continuous linear feature for each of the operational and seriously proposed MBTA Commuter Rail lines. The linework was extracted from the the Trains data as provided to MassGIS from the Central Transportation Planning Staff and modified by MassGIS to create one arc per Commuter route. Stored in ArcSDE and distributed as a shapefile, the layer is named TRAINS_RTE_TRAIN. Also see TRAINS_ARC and TRAINS_NODE (named station location points).&lt;/SPAN&gt;&lt;/P&gt;&lt;P&gt;&lt;SPAN&gt;Data are up-to-date through November 2, 2023.&lt;/SPAN&gt;&lt;/P&gt;&lt;/DIV&gt;&lt;/DIV&gt;&lt;/DIV&gt;</idAbs><idCredit>Central Transportation Planning Staff, MassGIS</idCredit><searchKeys><keyword>trains commuter rail stations transportation railroad railway</keyword></searchKeys><resConst><Consts xmlns=""><useLimit>&lt;DIV STYLE="text-align:Left;"&gt;&lt;DIV&gt;&lt;DIV&gt;&lt;P&gt;&lt;SPAN&gt;None&lt;/SPAN&gt;&lt;/P&gt;&lt;/DIV&gt;&lt;/DIV&gt;&lt;/DIV&gt;</useLimit></Consts></resConst><dataChar><CharSetCd value="004"/></dataChar><idPoC xmlns=""><rpIndName>Michael Trust</rpIndName><rpOrgName>MassGIS</rpOrgName><rpPosName>Sr. GIS Database Administrator</rpPosName><rpCntInfo xmlns=""><cntAddress addressType="both"><delPoint>One Ashburton Place, 8th Floor</delPoint><city>Boston</city><adminArea>MA</adminArea><postCode>02108</postCode><country>US</country></cntAddress><cntPhone><voiceNum tddtty="">617-619-5615</voiceNum></cntPhone></rpCntInfo><displayName>Michael Trust</displayName><role><RoleCd value="007"/></role></idPoC><resMaint xmlns=""><maintFreq><MaintFreqCd value="009"/></maintFreq></resMaint><dataExt xmlns=""><geoEle xmlns=""><GeoBndBox esriExtentType="search"><exTypeCode Sync="TRUE">1</exTypeCode><westBL Sync="TRUE">-71.850350</westBL><eastBL Sync="TRUE">-70.234306</eastBL><northBL Sync="TRUE">42.839668</northBL><southBL Sync="TRUE">41.476333</southBL></GeoBndBox></geoEle></dataExt><idStatus><ProgCd value="001"/></idStatus><tpCat><TopicCatCd value="018"/></tpCat></dataIdInfo><mdLang><languageCode Sync="FALSE" value="eng"/><countryCode value="USA" Sync="TRUE"/></mdLang><mdStanName Sync="TRUE">ISO 19115 Geographic Information - Metadata</mdStanName><mdStanVer Sync="TRUE">DIS_ESRI1.0</mdStanVer><mdChar><CharSetCd Sync="TRUE" value="004"/></mdChar><mdHrLv><ScopeCd Sync="TRUE" value="005"/></mdHrLv><mdHrLvName Sync="TRUE">dataset</mdHrLvName><distInfo xmlns=""><distributor xmlns=""><distorFormat xmlns=""><formatName Sync="FALSE">Shapefile</formatName><formatVer>ArcGIS 10</formatVer></distorFormat><distorCont xmlns=""><rpIndName>Michael Trust</rpIndName><rpOrgName>MassGIS</rpOrgName><rpPosName>Sr. GIS Database Administrator</rpPosName><rpCntInfo xmlns=""><cntAddress addressType="both"><delPoint>One Ashburton Place</delPoint><city>Boston</city><adminArea>MA</adminArea><postCode>02108</postCode><country>US</country></cntAddress><cntPhone><voiceNum tddtty="">617-619-5615</voiceNum></cntPhone></rpCntInfo><displayName>Michael Trust</displayName><role><RoleCd value="005"/></role></distorCont><distorOrdPrc xmlns=""><ordInstr>Download from https://www.mass.gov/info-details/massgis-data-trains</ordInstr></distorOrdPrc></distributor><distFormat xmlns=""><formatName Sync="FALSE">SDE Feature Class</formatName><formatVer>ArcGIS 10</formatVer></distFormat><distTranOps><transSize Sync="TRUE">0.000</transSize></distTranOps></distInfo><spdoinfo><direct Sync="TRUE">Vector</direct><ptvctinf><esriterm Name="TRAINS_RTE_TRAIN"><efeatyp Sync="TRUE">Simple</efeatyp><efeageom code="3" Sync="TRUE"></efeageom><esritopo Sync="TRUE">FALSE</esritopo><efeacnt Sync="TRUE">0</efeacnt><spindex Sync="TRUE">FALSE</spindex><linrefer Sync="TRUE">FALSE</linrefer></esriterm></ptvctinf></spdoinfo><spref><horizsys><cordsysn><geogcsn Sync="TRUE">GCS_North_American_1983</geogcsn><projcsn Sync="TRUE">NAD_1983_StatePlane_Massachusetts_Mainland_FIPS_2001</projcsn></cordsysn><planar><planci><plance Sync="TRUE">coordinate pair</plance><plandu Sync="TRUE">meters</plandu><coordrep><absres Sync="TRUE">0.000002</absres><ordres Sync="TRUE">0.000002</ordres></coordrep></planci></planar><geodetic><horizdn Sync="TRUE">North American Datum of 1983</horizdn><ellips Sync="TRUE">Geodetic Reference System 80</ellips><semiaxis Sync="TRUE">6378137.000000</semiaxis><denflat Sync="TRUE">298.257222</denflat></geodetic></horizsys><vertdef><altsys><altenc Sync="TRUE">Explicit elevation coordinate included with horizontal coordinates</altenc><altres Sync="TRUE">1.000000</altres></altsys></vertdef></spref><refSysInfo><RefSystem dimension=""><refSysID xmlns=""><identCode Sync="TRUE" code="26986">NAD_1983_StatePlane_Massachusetts_Mainland_FIPS_2001</identCode><idCodeSpace Sync="TRUE">EPSG</idCodeSpace><idVersion Sync="TRUE">2.1(3.0.1)</idVersion></refSysID></RefSystem></refSysInfo><spatRepInfo><VectSpatRep><geometObjs Name="TRAINS_RTE_TRAIN"><geoObjTyp><GeoObjTypCd value="002" Sync="TRUE"></GeoObjTypCd></geoObjTyp><geoObjCnt Sync="TRUE">0</geoObjCnt></geometObjs><topLvl><TopoLevCd value="001" Sync="TRUE"></TopoLevCd></topLvl></VectSpatRep></spatRepInfo><eainfo><detailed Name="TRAINS_RTE_TRAIN" xmlns=""><attr><attrlabl Sync="TRUE">SHAPE</attrlabl><attalias Sync="TRUE">Shape</attalias><attrtype Sync="TRUE">Geometry</attrtype><attwidth Sync="TRUE">0</attwidth><atprecis Sync="TRUE">0</atprecis><attscale Sync="TRUE">0</attscale><attrdef Sync="TRUE">Feature geometry.</attrdef><attrdefs Sync="TRUE">ESRI</attrdefs><attrdomv><udom Sync="TRUE">Coordinates defining the features.</udom></attrdomv></attr><attr><attrlabl Sync="TRUE">FID</attrlabl><attalias Sync="TRUE">FID</attalias><attrtype Sync="TRUE">OID</attrtype><attwidth Sync="TRUE">4</attwidth><atprecis Sync="TRUE">0</atprecis><attscale Sync="TRUE">0</attscale><attrdef Sync="TRUE">Internal feature number.</attrdef><attrdefs Sync="TRUE">Esri</attrdefs><attrdomv><udom Sync="TRUE">Sequential unique whole numbers that are automatically generated.</udom></attrdomv></attr><attr><attrlabl Sync="TRUE">COMM_LINE</attrlabl><attalias Sync="TRUE">COMM_LINE</attalias><attrtype Sync="TRUE">String</attrtype><attwidth Sync="TRUE">30</attwidth><atprecis Sync="TRUE">0</atprecis><attscale Sync="TRUE">0</attscale><attrdef>Name of MBTA Commuter line</attrdef><attrdefs>MBTA Web site http://www.mbta.com/schedules_and_maps/rail/</attrdefs></attr><enttyp><enttypl Sync="TRUE">TRAINS_RTE_TRAIN</enttypl><enttypt Sync="TRUE">Feature Class</enttypt><enttypc Sync="TRUE">0</enttypc></enttyp><attr><attrlabl Sync="TRUE">COMMRAIL</attrlabl><attalias Sync="TRUE">COMMRAIL</attalias><attrtype Sync="TRUE">String</attrtype><attwidth Sync="TRUE">1</attwidth><atprecis Sync="TRUE">0</atprecis><attscale Sync="TRUE">0</attscale><attrdomv><edom><edomv>Y</edomv><edomvd>Active service</edomvd></edom><edom><edomv>S</edomv><edomvd>Used for seasonal or special events only</edomvd></edom><edom><edomv>P</edomv><edomvd>Proposed service</edomvd></edom><edom><edomv>C</edomv><edomvd>Under construction at time of data publication</edomvd></edom></attrdomv><attrdef>MBTA Commuter Rail line status</attrdef></attr><attr><attrlabl Sync="TRUE">SHAPE_LEN</attrlabl><attalias Sync="TRUE">SHAPE_LEN</attalias><attrtype Sync="TRUE">Double</attrtype><attwidth Sync="TRUE">19</attwidth><atprecis Sync="TRUE">0</atprecis><attscale Sync="TRUE">0</attscale></attr></detailed></eainfo><mdDateSt Sync="TRUE">20231114</mdDateSt><Binary><Thumbnail><Data EsriPropertyType="PictureX">/9j/4AAQSkZJRgABAQEAYABgAAD/2wBDAAMCAgMCAgMDAwMEAwMEBQgFBQQEBQoHBwYIDAoMDAsK
CwsNDhIQDQ4RDgsLEBYQERMUFRUVDA8XGBYUGBIUFRT/2wBDAQMEBAUEBQkFBQkUDQsNFBQUFBQU
FBQUFBQUFBQUFBQUFBQUFBQUFBQUFBQUFBQUFBQUFBQUFBQUFBQUFBQUFBT/wAARCAGzAfsDASIA
AhEBAxEB/8QAHwAAAQUBAQEBAQEAAAAAAAAAAAECAwQFBgcICQoL/8QAtRAAAgEDAwIEAwUFBAQA
AAF9AQIDAAQRBRIhMUEGE1FhByJxFDKBkaEII0KxwRVS0fAkM2JyggkKFhcYGRolJicoKSo0NTY3
ODk6Q0RFRkdISUpTVFVWV1hZWmNkZWZnaGlqc3R1dnd4eXqDhIWGh4iJipKTlJWWl5iZmqKjpKWm
p6ipqrKztLW2t7i5usLDxMXGx8jJytLT1NXW19jZ2uHi4+Tl5ufo6erx8vP09fb3+Pn6/8QAHwEA
AwEBAQEBAQEBAQAAAAAAAAECAwQFBgcICQoL/8QAtREAAgECBAQDBAcFBAQAAQJ3AAECAxEEBSEx
BhJBUQdhcRMiMoEIFEKRobHBCSMzUvAVYnLRChYkNOEl8RcYGRomJygpKjU2Nzg5OkNERUZHSElK
U1RVVldYWVpjZGVmZ2hpanN0dXZ3eHl6goOEhYaHiImKkpOUlZaXmJmaoqOkpaanqKmqsrO0tba3
uLm6wsPExcbHyMnK0tPU1dbX2Nna4uPk5ebn6Onq8vP09fb3+Pn6/9oADAMBAAIRAxEAPwD9U6KK
KACiiigAooooAKKKKACiiigAooooAKKKKACiiigAooooAKKKKACiiigAooooAKKKKACiiigAoooo
AKKKztZ1Q6dDGsYV7mYlY1boMDJYjrgcfiVGRnNAF+SRIY2kkZUjUFmZjgADqSa4Hx14p1+8uLDS
fBkUdxcXTZm1ZWSWG1UHOG+9tJAPLDkZChm+7dmWS8kEl5K1y6ncqtxGh7bV6DHOCctz1NcX46ut
e0nXNHv9OiuL3TA3l3NtaQbpU55ZWUhwSpI4IGUGfvYq4bnp5bHnxKVot62Utm7af8BPR7Hr+nwz
29jbRXNx9ruY41WW42BPNcAAttHAycnA6ZrmPEFxNNrjGFVmjtYhGUJ2sGb5mwe52iPrxz1HNLDf
aja48q+MigbQl1GHUD6jaxPuWPfOTzUMfmySTTThRPNIztsOQOyjOB0UKOnaoPNb5ndjILyOdjHk
pMBkxSDDD3x3Ge4yPeqF9qcVxbg2yTTuH/dyRQuyhgeu4DleoO3JIJq5qDW62+bhQ4Byi/xFsHAT
/a9Mc0mkwy2+nQRTcOq425B2jPAJAGSBgfhQIZDrVnLGD56o/QwucSA9Nu3rnPaobezGoR/bJG2T
S7WhkjUB44+qrznk5OfXcR0xWpWbpca6cLyF3CqsjTBeipGxOMeg4Ppzn6kAbGZdFXZIzT2CJ8su
BviwAMMAOR7gZHOfWrjX0C28UxfKS7RHtUlnLdAABkk+mK5P4jfEbTfBfhe5vZo/tkrOtuli7NC8
rN1GdpKjZubJGOMZyRUvwy8Z2dzpFlrtvpcttp1+hEgZBJJbsrFXIcZJj3J0bB6EDqKdna50PD1V
RWIcfcbtfzNfUL6+ivIWSxn+yRmOUtJayqzyK4Kxg443EKMkd/wr0ivH9d1jV/EjC1mwLNrhpLdm
TarcHYoYqM8ZxkAndz7en+G/+Rd0v/r1i/8AQBSOc0aKKKACiiigAooooAKKKKACiiigAooooAKK
KKACiiigAooooAKKKKACiiigAooooAKKKKACiiigAooooAKKKKACiiigAooooAKKKKACiiigAooo
oAKKKKACiiigAooooAKKKKACuL1SOWbWtRdJdkscqopYFl2+Uh2kZHGSSORgk+pz2lcrrChfEFwF
G0NbxOcd23SDJ98Ko+gHpQBTt7jztysvlyp99M5x6EHuD2P8iCBNUNxax3G0sMSL9yRfvJ7g/wCQ
e9eK/HD4xah4ZtU8P6cjWerXERa5vEyPKTcygRd9zbSd38IIxknK1GLk7I7MHhamNrKjS3ZseAfi
Ei/EbW/C13q0mpSNcS/ZnlDEq6El4/uAD5QemFBQ7fvCvWK+eP2efhPew31r4v1IvaRIrGxt8YaY
OhUyNnom1jt7nrwMbvfdSmkhs3MOBMxWNC3QMzBQeh6E5/CrqW5tD0s79gsXag07JJ20XMtH5dr2
63Kkjs+stKIjNFaxhTgcozcsVGPmO3b0PQ9ycVpQzLNGHQ5U+2PqCOx9qIYlgjCIMKPx+pJ7n3qp
frbWqtdPKtpJ/wA9c43EDgMP4+B069cYrI8EtzTLDGXc4Ue2foAO59qqfZ3vp45ZovJSP7qlsueQ
eccAZUHgnOB05Bg0475t93GTcFm8mZ1IDDnhVblDjgjvjOTya1aAPLf2kdJ/tL4Yz3Hm+X/Z91Dc
7dufMyTFtznj/W5zz93HfNU/2Y9Ya+8A3FlJcJI9jeOkcI27o4mCuMgc4LmTBPoR247X4ifZNT8J
a1pLeTPd3VpLHDbyYI83ZmMknhTu2kE4wQDnivA/2a9YubXxFq2nwtKkNzaCZnghEjKyOFUkH+HE
rZxz0reOtNrsfV4f/aMmrU+sJJ/f/TPpbXpo4NHunljEqbcbGGQSTgfrium8JkLoscO4kwySRbWY
kqoc7Qc8/d249iK85uItS16aLT1SeQTy/I15AIfLwCeoOD8u7PHbgV2XgXUDLHJFKG8y4VblXYY3
4REfA7AELycZ3cDAzWB8odbRRRQAUUUUAFFFFABRRRQAUUUUAFFFFABRRRQAUUUUAFFFFABRRRQA
UVwn9kWP/Plb/wDfpf8ACpVttqhUnuo0HASO6kVVHoAGwB7CgDtqK4G6WSOa0Vbu9AklKt/pcvI2
Mf73qBV1Jr2FQkWpXSIOitskI/4E6lj+JoA7GiuQ+1aj/wBBW4/79w//ABFTf21q3/Pay/8AAZ//
AI5QB1NFchdeIdWto1fzLJsuiY+zuPvMFz/rPepv7a1b/ntZf+Az/wDxygDqaK5Zdb1VWBL2cgHJ
QQuu72zvOPrg/Q06PxZeySyx/wBnQBoyMg3bcgjII/d9Oo+oPpQB09Fc5/wkt9/0D7f/AMC2/wDj
dSr4qwoD6bdb+/ltGVz7EuCR9QPoKAN6isL/AIStf+gbe/nF/wDHKZF4wjmUsmnXpAYr/wAsuoJB
/wCWnqDQB0FFYaeK4dw82yvIE7yMqOB+CMWP4Cpf+Eq07+9cf+Ak3/xFAGvRWM/i7TI1ZmknVVGS
zWkwAHr92nf8JVp3964/8BJv/iKANeisj/hKtO/vXH/gJN/8RUq+JNJKgnUrVD/dkmVWHsQTkH2P
NAGlRWd/wkmk/wDQUsv/AAIT/Gj/AISTSf8AoKWX/gQn+NAGjRWd/wAJJpP/AEFLL/wIT/GrVrfW
9/GZLaeK4jB2lonDAH0yPqKAJ6KKKACiiigCK6uorO3eaZ9ka9T19gAO5J4AHJJrj2v7jVpZnlnu
INkjKsEcpj8sdRkoeSV2k5JwScY6Vo6/efbLxbRD+6t23zdsvgFF9wAd312YPBrIj/c6lMnRZkWQ
D1YfKx/Ly/8AOaAJIbRbXH2Z5LPB3BbeQou71Kj5SenUHOOaXy7iS88+a6a4Jj2Euihjg5HKgDAy
3bPzHJPGD7ZB9o8jzo/P/wCee8bumen0rPvru2hsb6/1KTZY2ayPLEy7lVEBJZgASx2jcB6EYBOD
QNJydkS+INdtPDOh3uq3z7LW0iaV8EAtjoq5IBYnAAzySBXyTJcar8cPiYkps5pFndd1vby8W1qp
AOHbhcDJzjBduBlsV2HxO+NnhrxZ4Nu9J0nRrmC6uWjBmuIYoxGquHJBVmJJ2gY46k54we1/Ze07
7N4Dvbp7XypLm/fbO0eDLGqIBhsfMobzB6A7veumKdOLk1qfa4WjPJ8FUxdWFqjfKr9E+v8AXY9U
hkvJoUnje3kR1DrHtZeD0+bJ/wDQefQUxbjdeobtfs7L8sSscqzHAyG6Z6gDg4zxzgTSf6DMZBxb
NkyeiN/e9gec++D/AHjVl0WRWVlDKwwVYZBHpXMfElOG8ubyFJYLdY4pFBDTv83POdq5yPxB+nWp
4LURsZHYyzMMFznA9lH8I6dPQZyeaqWtxbaaJbaWWK3CSMUDsEyrHdkD0BYr/wABq5b3kF1u8iaO
bb18tw2PyoAdcJFJC4nVGhxlhIAVwOcnNVIILh1ISZ4LcnKiQb5ceuW6ZPYgnnt0Dt66kwVGElmA
d7KeJDxhQe69c/gOfmFXaAK1vp9vayPJHH+9b70jks56cbjk44HFfJngW9T4e/G1rW3N1Naw39xp
ojRvnmBZo4w+MAjfsY8dsgZAFfWVxeBWMMBElxkAqASEz3bHTjnBIzjAr5g+Ogn8I/GC01mNo57t
kttQAZSI98bbFGM5x+6Gee55HQb0tbx7n1WQy9pOthX9uL+9f8Oe+3HiO9m1KyhhtHt76OZGijMo
wzHGA3AOCCRjI+8c1rSalaaH4ukitZfKtorhFIx+5QvgSJuB4A+ZsHA3L0G35ue1rWZb7V7V7GSK
VIds9tPEQysCquHznaRxnPTFXr2EyF7xVs1ujKboXUbZhIcpG45ycq5VhzjluBjFYHy22jPWaKyP
Cskj6LCroypGzJEWxhogxCEY6jbgZPJxnnOTr0CCiiigAooooAKKKKACiiigAooooAKKKKACiiig
AooooAKKKKAOPooooAqXv/HzYf8AXc/+i3q3VSb5tUtgeQIpGA98oM/XBI/E1boAKKKKAKl980ln
GfuPONw9dqsw/VQfwq3VS9/4+bD/AK7n/wBFvVugAqG4t/O2sreXKn3HxnHqCO4PcfyIBE1FAEFv
cmZnjeMxTIAWXIIwc4II7ZB64PHQVPVST/kLW3/XCX/0KOrdABVTS/8Aj2f/AK7zf+jGq3VTSP8A
kE2X/XBP/QRQBbooooAqav8A8gm9/wCuD/8AoJq3VTVObMofuyPHGw9VZwrD8iat0AFVtRme30+6
ljO10iZlOOhAJFWaqTX1s++Ef6S3KNFGu/2w3YZ/2sDrQBLa24tYyu9pGZizSPjcxPrgD2H0Aqas
q1QRalEsdmLFGjdiF2gvgqOQuRj5uvX6DOdWgCG7t/tVtJDu2h12k4z+B9vyPuOtVoLe3vlP2i0i
aaE+Uwk/eEY5HzEZOQQfx9alk1K3jjlcSB/LYxlVPLPjOwere1M02GaP7TJNkNNMZFVsZVcAAHBI
7etADv7Isf8Anyt/+/S/4VV/suyk1Mr9kgCxQglfKXDFmOD07bD/AN9Vpq6yDKsGGSMg55BwR+dZ
l5NINSilgDiOE+Xcsse8EEAgYB3EjIxgHG4+4oAux2UcK7YDLap1KW0zxKT64UgZ9/an+Q3/AD9X
v/gZL/8AFVD/AGlE/wDqVkuT2MSEqfo5wv6+3WmvLfMrMsESYG4Izlmb/Z6AKT65IHvQBbjjWNdq
9OvJySTyST3JPeq11+7vLSbtuaFiegDDP57lUfj702TWLSNokMpMkgJWNEZm465AGR0PX0PpVa6b
+2pBaCKRLVWDTNINhYdQAp+bBPfA+6cGgCfTo0vNP3zRBluGaXbIA2VLErnr/Dt+mB6Vl61pdtda
Nr2jtPFp8d9A0Sy4AWMSRGPOMjJBVjj9a6OmeTH53m7F83bt34+bHXGfSgqMnCSlHdHw74etbHTf
Ff8AZ/iC0jlgErWs+6UgQuGxuDo4GARgnJG0k9cGvt6xS3jsbdLSNIrVY1EMca7VVMDaAOwxjivl
b9pa4spviUUtQgnis4ku9qbSZcsw3HHzHy2j554wO2B9KeGLO70PStN0+/n+03C2qLJPvL75wo80
7m5O45YZ5PzemK6KuqUj6/PpvEUcPipOzkvh6dNV/XY3KqQ/6DIlueYnYiI+nU7MegAOO2BjsM26
juIFuYXiYkBh95eoPYj3B5H0rnPjiSoLqzivFxIgLAEK+Blc9cZ/UdD0ORRZTtcW6s4AkBKPt6bl
JU49sg4qegCj9te3m+zOjXEu3cpjK7mX1IyMHrz049Ttp/2ee5/4+JfKT/nlbsR+b8E/ht9Dmqmn
6eIPOhinmt3RzkKwYMp+4RuB4C4XIxypHOKsNb3kciTLMs78q0Tfu48HuMAnOQOpPfpmgC3DDHbx
iOJFjQdFQYA/CvC/2pvDMt1peka5BboyWrPb3MqoTIFfBjLED7gYMOTwZBj7xr2GHxApsorq4tpI
IH6yqVkReuM4Ofbp14rxH9qLxUZLfR/D4hMTljfTLIBuAAKRkEMRg5lyOvyjp31pX51Y93I+f+0K
fs/O/pZ3/rudJ8E/Feq+IvhylrDY75rJjY/axIqblVV2HGByqFV6k/KCetd3pvhSSxmtZ/PVJFV0
lCqHDBgwyNwIPBAwR61jfA3w2vhv4a6Uu1BPfL9ulaNmYMZACh56ER+WCBxlT16npJLqTW7pLaKO
VNPK75ZmVk80dlU46HIz6jP4zO3M7HFmDpvF1XSWnMzWsvFV1b3k1qbi21NuCollEUiHkFflQhum
egI79q6uwv4tRtxLFkYO1kbhkbupHr/PIIyCDXiU2yD7dFJYRxOQrorykGIe2Tljhhx7ZIwOOqsp
7vTtKi8Rafes1uq+TdWt2/nMP3mF5AXJ+bcM4Iz1IOKg889MrM1rXE0dYkEEl1czBjHDHgZ2jklj
woyQM+/Q1mWvjy0axhubuGW1STBMiDzY1yD1ZeRg4ByByeMgE1z2hXH9qtPqUjSSTzHafMcMEHUq
o6quScKT0ANAEUmpaxHazXlzrDx3EEojEiLmHbjHKAAH5m5OCRt4GRXplfM3jL45aX4b1rUvDd7p
l5NHA5aS4t3QEuZd+0Ke2w/ez14245r2xvFGqssEItLG3ubiTy43muGKKTlgrALycDbweSR9Kpxa
1Z1VsLWoRhOpGykrrzX9M62iiipOUKKKKACiiigAooooAKKKKACiiigAooooA4GbTXmhdWvLguVI
R923YfXCbc/j6VLYXn262WQxtC/R4n+8h9D/AD+hFTu6xqzMwVVGSzHAA9azI9Na7huJnklgmuCX
TY7p5Y2gLlQ2CwAGffigC1J/yFrb/rhL/wChR1brK0+xtbiN1n062jniby5AsalScA5HHQgg81a/
smy7WkKHsyIFYe4I5B9xQBboqpHdi3Vku5FjdMnzHIUMucBs9M8gH3PTBGTzLm6/1a/Zov8AnpIM
ufovb6nn1WgBsjqdYt13DcIJCVzyAWTB/Q/lV2qR0e0eExyQJLkszM6jcWb7zZ7E+3t6U5bp7eaK
3mDO0jFUlUcNgE/N6Hj8eo7gAFuiq17qFtp8Ye4mWIHpnqfoOp61DJPcXn7uGF4oSVzPIdhK5+YA
feBxwOnUnIwMgBeSPHqdt5cRlYwygDIAHzR8knt9Mn2qTzL7/n2t/wDwIb/4ioUtYrXVoDGuGaCT
c7EszfNHjLHk/jWjQBU+2TrwbGYnuUeMr+GWBx9QKqaVJdQ2EQ8vz448xbOFkXaSvrtPT1GB3brW
tVTTeIZVPDLPLkdxl2I/Qg/QigB0N/DJIIi3lTn/AJYyfK/vgdx15GRweas0yaGO4jMcqLIh6q4y
D+FV/sMkPNvcyJ/sSkyqfc5O78mA/XIBDrU0cUNussvkRSTqrSd1xllPPH3lHXjGam+0S2nFwu+I
f8vCkcD1cdvqMjqTtFQP5l1fW8F1AiqFeX5W3q3ATByB2c5GPTnqKbp832GcadKjIRuaBy2VdM5C
gnnIBxj0FAD9U1WK3026mhlV3jQY8shipb7px6cg/Srdrbi1h8sOz/MzFnxkkkk9AO5qD+xrFZop
ltIkkjOVKqF59cDr+PSrtAEFxaLcMjh3ilQELJGeQDjIweD0HUVSuraXzLUz3MjBpdr+UxiQAq2O
hzy23qTz0xnFalUtWUtZgBihM0QDLjI/eLzzQA4w2unsJtm1yvlggF3bknAHJJyST3PU9KPJlvOb
j91F/wA8FIO4f7Zx+g465JBqSCzjgYyYLzEYMshyx9s9hnsMD2qegDFTRLaeeaIh4FhnWVEicoMb
Qc4/3twz14wDxirDRf2TM0yK8lvKVEpaUsYyMjf8xORjAPPAXPPaf/V6t6+dB+Wxv6+Z+nvVl0WR
WVlDKwwVYZBHpQA6vNW+P/heHxZNoN0LyymhuntHu7iNBbq6sVyWDkhSR1I4zk4GSO/+zz23/HvL
5qf88rhifyfkj8d3oMV4V8bPhNDrMF94q0K1a1mhRp9QgfaiSgDc8i88SDncOjbT/EDu0got2kev
llPCVq3ssU2ubRPs/M9vvLWOGS38keVLJdCT5ehO07s/VQ3Tvj61buLWO42lhiRfuSL95PcH/IPe
vCv2a/HV3rTzeHdRlkuf7Pt/OsXYA7I9yqyMc5ONy7eOAXGcbQPe6mUXF2ZzY3CTwNeVCetvxRU+
0SWfFz80XQTqCf8AvsAfL9enB6cCofEWrf2B4f1PU/K8/wCxWstz5W7bv2IW25wcZx1xWjXnvxk1
JPDPw91h7aJj9ot2t2gU4jCyYjL4wcYMgPGMk85pR1aRjh6fta0Kdr3aX3s8R+CfhFviV4+vNW1l
EvbS1Y3l2JEXbPNISUUqCOC25uhX5NpGGr6pvIGnhPlkCZTvjY9Aw6Z9j0PsTXgX7KZe3/4SBnhl
WG4aCOKbYfLZ0EjMm7puAYHHofcV9CVrWfvWPc4gqynjpU7+7BJJdtEyO3nW5hSVQQGH3W6g9wfc
Hg/Sm3F1Hb7QxzI33I1+8/sB/kDvUDOtjdfMwS3mBPJwFcZYn8Rk+nynu1JYzLdXl3Ohyg2Qjjrg
Ftw9jv8A0z3rE+bEj+0W8ss7QARSEM8atudcDG7GOTjGVB428ZJqS4v1/s+5uIGWQxIxwezAZww6
g+3WrdZWrxYngk86W1RyUmmjYKAoVtuSenLcfX1xQBetYY418xHMpkAJlZtxb059OTwOOeKfPcRW
qhppUiUnAaRgoz6c1DuttLhihXEagYSNAWY464A5PqfzqotuurXE0k6ywmBlWOMv9xwN2/AJXPzD
rnp74oAXQjNJDLOyrHBcN50ce5iy5+9nIHBPPHHJr5P1y+uPjd8WEWzE1vDfSpBAs7hzBAi/M2CQ
BwHkKA9SQCScn3742eIZvCvw51TdLFO18v2GLzkO4mQEMPlGCdm8gnaBtH3uh4H9lrRreBdX1ud4
lmkZbC33OwbjDyDH3TkmL1Ix2zz0U/di5n12U2wODrZg173wx/r7vuZ65caHJpFpc29hHFa6WsYY
RRs2AqKcpt7buB8pHC10yIsaqqqFVRgKowAPSoNQtftllNCApZl+Xf8Ad3DlSfbIFS2863MKSqCA
w+63UHuD7g8H6VznyW+rMJoVvL46jc2Gy1WJgscqL5jvkAZXuT0AOenbIpbHwhaR+YbmMSMxBVVd
tq8DIHQ9c9c8Ae9aupfJDHMeY4XEjr2KjOT+Gd31UVi/EHx1ZfDzw3Jqt5G85LCGC3j4MspBIXOM
KMKSSegB6nALSu7IunTnWmqdNXb2KvjC+uZrkWSBo7cbdzMNquxzjLHjHH5g+ledeOvjOnw/0+98
PaWpm8Qq5DXBiAhts5555kfABGRj5hknaVrybb40+NWtahLbxTak4YTyQRyCO3g/hUAMwUHGQOdx
AY88mtbT/gv4j0DxHpNzfWVnd6T9qD/afOSSCdI2BcbT8xB+7gqM59Oa6FTjF+8z7OjlOEwU+bHV
ouSV+X+nr6W1Lnwe8Ian4o8dWnizWYQNL+0yXkl7cHyVnnBJGzGMkSENgYX5GHbFfTt9HdCGz1CW
NrLT7e7jkmefcr7Vbr5YBOCcYzznHAHNGm6HFfXNrpdxGsViloCLe1Plxq0bRjaoAGFwcYz07AgG
u8jjSGNY40VI1AVVUYAA6ACsZy53c+czHHyzCrztWS0S7IqWMd+Li6e8lhMRfEEcKn5UBPLE9WOR
kdBt461dooqDywooooAKKKKACiiigAooooAKKKKACiiigDgNZkUWqxPFLMkzbGWE4YgAsQPXIXGP
Q1Lptn9htVjJLOSXf5yw3Hk4zzjP+c5pG+fVo8c+XA2723Mu389jflVugCpbfu7+8j67tk2fqNuP
/HM/jVuqUai11BwclbgblZiSQw6pk9sHIH+/V2gCjrMnk2DyBWaRWXYUGWViQoIHc89O/TvVxNwV
dxDNjkqMAn6U24t47qF4ZkEkbjBU1kw2D2+sxLBLLHbxh3aF2ARg2T8gHXDHnPT5fagDaqC7tjcq
m2QxSIwZZFAJHY8HjkEjn1qeoLqdowqRgNNIcKp7DIyx9gDnt2HUigCvZwhb6V43d0C7Hkdi3mOC
enpt56cZYjtV+o7eBbaFIlJIUfebqT3J9yeT9akoAqf6zVvTyYPz3t/Ty/19q84+Ifx/0XwTeGws
ov7b1KKUx3EMchjSDA5BfaQWycbRnGGyQRgyfHHxhN4Q8K6i9ncS2uoXiQWtvNDjcmWkZzk8j5FY
bhyCy4x1HlvwM+DFr4yt5Nc11HfSlZooLQF4/tDAYLlhg7ATgbTywOSNpDbQirc0tj6XL8Dhvq8s
djX7idklu3/Xp5ux6F4X/aW8O61cWdrqFrc6PczsUeSQq9tEcnbmTIODxyVABPPAzXqdj80l5IPu
POdp9dqqp/VSPwrwP4qfs7S/aLS68F2CGAr5U9ibghg2SfMDyvggjCkZGMDAOTjkfCvxY8VfDXxR
c2WuT3d7CsnlXlpeyGZoyGyXjJb73JPB2sD16MKdOMleB11MrwuOp+2y2Wtm3BvX/gfPTbU+taKz
tH1WLVLW3mil8+C4gS4gn2lfNiYZDYIGDgjIx3HTOBo1znyDTi7MqR/Nq02edsEe32yz5x9cD8hT
NUjcLBcxR+ZLbvv2hcsykEMByOcHP1Ap9jzNfMOVafg9jhEB/UEfUGm6prWn6HbrPqV9bafAzbFl
upliUsQTgFiBnAPHsaBxi5O0Vdhb6zY3QTy7uIlzhVLAMTnGMHmrteMD9obwhoomtSL3VxK7SPc2
tuAkm491kKEHHUAY96vaX8ePAF9btJJc3eisG2/Z3hlQtwPmxDuXvjk549MVfJLsek8rxyjzexl9
36bnrNVNS5hiUcs08WB3OHUn9AT9Aa830H47eHdc15tLttRuYWYsIrnUbVRDMQeAhVgwLDJAYDPA
4JAPootpb9Y3u08jb8yxRSnIbHUsMc4JGBx168Ylxcdzjr4ethpKNaLi33L1FVbCRyssUrmSSGQo
XIAyDhl6AfwsO3XNWqRzlTUPk+zS9fLnX5fXdlP035/CrdQ3lv8AarSaDdt8xGTdjOMjGajj1CNr
GC5lIiEqqwXOTkjO0ep9h1oAtVUu/wDSpPsg+4y5m/3DkYHuSPyB6HFR3GrLbwvKYJVjx8jyDYrN
2BzyvPGWAH6VZtbf7PGQW3uzF3fGMk/07D0AAoA+NtUt9S+DXxKma3t2SWzllaya8+YSwsGRJMqQ
Gyp7cZBBHBFej+Df2obltQit/EthbrZyMqG8slZWh4OWZCW3jO37uCBnAbgV9EV578SPgtovxC33
X/IM1ptg/tCJS25V4w6ZAbg4zw3C84GK6PaRl8aPsP7WweOcY4+lra3Mnr62/Hr6M7HQvEOm+JtP
S+0q9hv7VsDzIWztJAO1h1VsEZU4IzyK82/aY1c6f8O0tFWNjfXccTb1JKqoLllPY5VRz2Y/h41q
Hhvx58EdQkubaWa2gKhmvLEmW1kGAo3qRjgyYG9RyeOxpnxC+MN38Q/DdnZXlpDBeLdGad4VIQqq
lYgmWJH+sl3A5/hIPYVGn7ya1R04XJXDF0sRh5qpSve/VW11/r5I9g/Z00W4HwtuWkiVDd3s09pI
xB6IkYcY5Uh0YevGfSvU7ezt7q3imVrkLIocBrmTOCM/3q+XfgL8Sn8G65JpVz+803UmwAzN+6nA
IQqACPnO1Dx/dJOFwfp9bxNOt0s4g93cwxonlxoeuMDcei5xnk9KyqpqWp4ueYepQxs5T2lqvT/g
f8EsJpdlGystpArKchliUEH16UtxC6yJPEMyLwyjjzF5+X6gnIz9MjJoh1C2mkEazKJT/wAsn+V/
++Tz09qrFLvUCZoLw20OWCKsatuGMBsn3yeOox0rI8AvwzLcQpLGdyOoZTjqDyKr3Ekk0z2sSx/c
DO0wLLhsgDb/ABfdOeR269KzdHk1GOzSXyhcQyHzNjFVk+baxYEfKRkucHB6c9qs6WxkvLqWY+Xc
y7f9HLE7FUY4yBkZLcjj0NAFqw0+LToikWTkklmxnqTjgYA5PAGOaimaXT2UQokkU0h4kcqI2OT1
weCf1OO4Av1RvtQskmFjcyYe4XaI8N8wbjqOlAHhP7UutXP2fQdKeSCNGaW6lt45A7ZACxucqCo+
aUDsefSvRPg/oMug/DXRreO2tJluoBdySbihkMo3/MNhyQpVck8hR9K8T/aTme48YaLLIdzvo0LM
cdSZJSaz7z9oTxhJ5CWFxZ6LawxLElrY2aeUAOmA4YjjAwCBgDiuvkcoJI/QFltfGZXQo0GktZO+
ne2yfc+ptstrvVGW0lCNIqNKZICox1yAVAyOmByOuMCSzs/tEZmNzOROd8kYwnzYAxwNy4wBjd25
zzXz3Z/tRX6aHDb3ug29/qkScXrzbUMgztkMQTr0yAwzzjbnA5rVvit46+I0d/YWMLi3mgL3lpo9
qzboxgM7H5nVcbVOCFxwRyc5+xl1PHhw7jHJ+0tGK6t/j/w9j274h/Fbw54FsyIbltZ1TzTF9gtt
RfKFTh/MYE7MdMEZJ4xwSPn+6vvFPxq160hKeYluiQqI1ZbWzTABdzztB25LHJOMDoAO4+G37Let
eKDFdeIZJtAsTtcwmH/SHGRlCGI2EqeGw2O4yMV9GWXwp0PSbc2uk6YulWySopjjlJW5jzGWLZy2
75SM5BJXJPNVzRp/DqzseJwOTpxwn7yr/M9l/Xl82Ymh+FbHwZ4fg0DQrdlklV1jw6iWWTYS0rsS
MngZPbgAAACtfxhcHT9LsNFgVnuFiWIXPlMGOzYVWP1LME+6TjHPt1OieG7LQYsW6F5cYNxLhpCO
MDdjoABwOOK1K59z46c5VJOc3dsxvDOjSaXZ+bdSPLf3CqZ2YjC4HCADgAZPTqSTWzRRSICiiigA
ooooAKKKKACiiigAooooAKKKKACiiigDgWt3st9yjyXEm394G5aRRnAAAwCMnAAwcnPXIuI6yKrK
wZWGQynII9adVSb/AEFjMv8AqGbMif3cnlx6Due3U9c5AJbq3+0QlQ2yQcpJjJRux/z1GR3otbj7
TbrIV2NyGXOdrA4YZ74IIqaqNnII7+8tj8p3CZFyMFSACQP94Nn3PvQBeqpfMJMRIjST/fXYQDH2
DEnoOvrkZ4IzSvcG4ZordwSpxJKuCI/b3b27dT2BmggW3UgEsxOWdurH1P8An26UAQfbDa/LdsoJ
+7IikK/sByd3tznt3AW1jk86aeVQjSBVVc5IUZwD27njnvyRjE80SzxlHGVP4fQg9j71DDM8Ughm
OWP3JMY3+x9G9u/UdwACzRRRQBzvi7wpF4tsb2wu4hNZ3UAhP+kNG0ZD7ty4UjOQh5/u8gjiovBf
hv8A4Rfw3a6Zp0+y2tmkjCXC+b0kbJyNvJOSe3PAA4rabUGx5iQPJbgjMi8lgTjKqMkj8uORmjR3
VtNgAYGRVAlGeQ+MsG/2snnPPNO7tY19rP2fsr+7e9ul9riR6bJ8zS3czyuxLFGKrt/uhecD3Hze
9ebftCeAR4k8G/2laqq3ejI0yoqgboeN65yAAqjd0J+XA616vRTjLld0a4XETwtaNeG8X/S+ex86
fs+/EQLpd54b1C4hhWxie+06WUpGF2kvKjMSMjkt67fMyQAMU/iD+0lql3qklt4VkSx06JgFvJIQ
80+Mgna4IVDkYGN3ygkjJUM+KP7P2rWuvXOoeG7ZLzS7gvcNArxwm1OclACVBTn5dvQDBHALdr8D
/gvL4SjuNV8Q2sP9rS/Jbw7g7WqjILBlJXc3HK8gDr8xA6X7P4z7atPKouWYu03K1oab9br87q27
1ujymz1b4sW+of2jAniZpHZpQptZXgJfJJERUpj5iQNuBxjGBUei/B/xv8QNQuri9imtZwoMl1rj
yI7kABRggueBwcY+UjPGK+sk03yVVILmeCNRgIrBx/4+CR9OlV7dTp+rFJZhK16CVbywpBQAYJHX
I57Dg4HNR7Z9EeZ/rDUgm6NGMXte3Q8u0D9mjQ9L/wCQgX1uQqVLSztBGCTkMI0G7IHGDIQeemRh
kn7LHh1lTy9V1NWA+cs0bAn2GwY/WvaaKz9pLueT/a+P5nL2r1/rbZHy78TvgMPCOiyX+kPd3v2Y
h7hJCr/ucHMgwqkbSBuA3YEgOQFJPefs/wDxYvfF8cvh/Vg9zf2cHnR3xOTLEGVcSdy4LL838Q68
jLer30xgvrNo43mlYOpjQD7mAScnAHITqe5r5Lv0f4RfGJLmKN4LC2vPPhESli1o5IKL5mMsELRn
PRlYZyM1rF+0i4vc97B1pZzhqmExGtSKvF9fT+v0Prye1EjCRGMUyjAcZwfZh/EOvX1OMHmmw3f7
wQzhYZz91d2Q/upwM+/GR9MEy29xFeW8U8EqTwSqHjljYMrqRkEEcEEd6gvP9ImjtR0P7yQjqqjp
g9iTjB9A2CCK5j4vbRk89xFaqGmlSJScBpGCjPpzVTSbdVjeco6yPJIR5m4EKZCRgH7uRg9s8Uy+
s47ezmnwZJowJTJIcs2xg+3PYEr0HAz0rSoEFUrNFtbqeBVEaYDxRqMLt6HA9c9cccr3Jq7WdqMx
+2WUUIWS4DmTy2JAC7GGSQDgZIHuaANGiqn2a6+/9s/ef3fKHl/l97/x7r+VN8y4tpYjNIkqSN5Z
2psCcEg9T1PH4jGO4BX161W6W3V40uY2do2tZE3LMrKQykEhfubuv078/N3x2+FaeHbz/hINDs9m
g3H+vSLpazFiCNuPkQ8ADoGyvy/KK+mLFXuJ3u3fch3JCmPurnBIPcNtVv5UmqW8X2W5kliSa3eN
hc28ihklTGCCDwTjjngjg9iNITcHc9XLswqZfWVSOq6rv/wex8Q6xeWGqafY3EEEOn31vElrcW8K
MFuNoIWcHkBiAA44y2GGd7Bfov4A/FO18RaXHoOozsNeh3OJZ2BN6uSdwPd1HBBySF3ZPzbfE/iF
4bufhf8AEGaKGNI7dj9ptY95ZGt33AxtzuK43xndgsAc8GtPxN8Nbm30228ZeEPNm0NoxdnyZR5+
nOpG5ThixCnkMCSoB3fd3HrkoySR+gY2nhcfQp05ysp6wk+j7f8AA67bpH1drCLLp8sTKGEpWLkZ
wWYKG/AnP4Vdr5p8FftHXb3NpZ+LV+02e/DX9sBG653fNIij5gpK42bSNucMcV9BXVrewwXMiX80
hVC0UYiTOQOh+XnJ9MVxyi4PU/O8bl9fL5qFZb7PoyzD/oly0J/1czNJGfQ9WX6kksPx6Yqee3iu
lCzRJKoOQsihhn15pjLHqFnwx8uVQyuvBGeQwz0I4IpkN4vnfZpnRLrGQoON45+ZR+B47Y+hMHnC
fYZIebe5kT/YlJlU+5yd35MB+ucbxJY6lNbCUSwslv8Avd0e6NwR143EcDnPX09+kqjdR/2kzWwZ
kgRgJypwW4zs+mCCT6cdzgA+Tvj3fT3Pjz7Lc/6+xtIbdgFUKMgyADHYCQD6g9sV9UeCfBOm2unm
x0vULaKyhYrPb6bB5R3lAoPmZ3NjaMOQS23kmvmDwvpcXjD9ofyLeVJ4JtauLmOWMq6MqO8obrhl
wueDyOh5r6qsLi48Nw3cOmt9uhhlLTG5jYSTyjAk2EHgcYGQ3zZ6jmuipolE+tzuXsaOGwifwxu/
O/l8mWLX4MeB7WRJf+EY0yWVerS2yMGOMElcbfyGB2xVibR9I8IrIzTDT9CmiNqulwRFYEZuWKKn
C5AYnA6sTnmrGn6laW/hW41eC3lhS4L3Eq2pMrq5O1mG8AcYyeMDB6jrej0+HUItIuEuXuILdA6+
eofzgVG1zkZDg4Ibryw71hdny8qtSorTk38zUjjSGNY40VI1AVVUYAA6ACnUUUjIKKKKACiiigAo
oooAKKKKACiiigAooooAKKKKACiiigAooooA4+iimu6xqzMwVVGSzHAA9aAKy/6DMkfS2fhc9I24
wv0Pb0Ix3AEMkBvNQWSORkjjRopGUn5skHC88EYwSPp1HyzeW9980m6O37QkYLj1fuB/s+nXrgG1
7DhI2ltv7qctH9B3X2HI6AEYAALKIsaqqqFVRgKowAPSnU1HWRVZWDKwyGU5BHrTqACmTRLPGUcZ
U/h9CD2PvT6KAKUV8kMxtp5kMikAPkDdnoCOze3fqO4Dv+Qh/wBen/o3/wCx/wDQvp95tuizNMyK
DZyD7rDIcnqwH90/r192u0AFZs0y/wBqeb5LskK7HljXJ3HBCkD5iACOACPmzxtrSqlausN9cWoY
dBOi55AYncPf5gTn/axQBJDqFtNII1mUSn/lk/yv/wB8nnp7VZpk0MdxGY5UWRD1VxkH8Kr/ANmx
J/qWktj2ETkKv0Q/L+nv1oANR+ZbeIfeknTHp8p3n9FP44q3WbPFPazQTvOLiNGCBHTDZdgu7IOM
jP8Ad6EjvmtKgArOu0Eer2MomYPJui8rI2ldrMSB65C8/StGsa1tbma4XVEmWVpYiqwyDaAhbco3
AcEDHY8559ADZoqtDfRySCJw0Ex6RyjBPfg9G49Ccd6dfQNc2skSkfMMEN0Yd1z2yMjPbOaAI7D9
9vuz/wAtsbP+uYzt/PJb1+bHavJv2kPAS634ZXX7OAG/005nMafNJAcAk4Uk7DhuSAF8w16uuqRq
WSSOUSodrrHE8gBxnqBjoQfx6CoNQu7PUrWSySS3ujdKYTESsilWBDEqcggLk4PBxjvVRlyu52YP
EywdeNePT8up5F+zb4wvPEGj3mg3t8T/AGcEa3Bcec0JyCg77EIHI5G9QCAAK9rt7WK13GNcM33n
Ylmb0yx5P418ezxN8G/jAFSZ5INMvFbdGFeRrZwCV5AG8xPg9BknB6Gvp/wz8UPC3jC8a10nWIbi
6HSB1aJ34J+VXALYCknbnHetakdeZbM97OsC1V+t4eN6c1zaLRevrv8AM6aaZbeF5ZDtRFLMcdAO
TVCx0kR2sYZ54pMZCrOxEfcLjODt4HTBxSaxqNpZYe9uobOyg2zTz3EgjRfmxGCxIAy3v/DjvVH/
AIWJ4U/6GbR//A+L/wCKrGzPmo0qlRXhFv5Gt9im/wCf+4/75j/+IqPTIfKuL/LGSTzgDIwAYjy0
IBwB0yan0/UbTVrOO6sbqG8tZM7J7eQSI2CQcMDg4II/CoUtbi1kmeB45FkcyFJQwYk8ffycAYGP
l6AD3pGbTi7MvVR1SWNoTbEK0ku1QGXcq5OAxzx15APUjApV1SKaxa5hIlwdgQMPv5wFJGR1IGen
OelTQ2qxwukmJTISZCw4Ynrx6Y4A9ABQIkhiW3hSKMbURQqj0A4FVdadY9JvSzBR5LDJOOSCAPzp
pu201Y4Zklm5CJKo3buw3Hs2cDngkg+uJY7MNMtzOA9woIXBJWMHsv8Aj1PsOAAeV/tM+G11TwLF
qqqgn0udWLszA+VIQjKoHBJbyjz2U4PY537NOqT33hWfT/tyL5E8gEKKvmRR/IwP/Amd+WB+4QDx
x2vxq1a1034a6+J4I7xpLcRrA+DtLuEWTocbWIYH1UDIODXjP7M+g3snia41lFCWkS/ZAzq2Hdvn
IB6cIhJ5yCycYOR0LWk7n19D99klRVHZQlp+Gn4/iav7Qnwti0yxj8R6bHtii2w3SJFGo+Zm/esV
CksWZRkhic8kY57H4GeKtQ8QfDNIZriNbyzuP7PtGVBuaNEjK5HfaHwSB90AnJyTr/H91X4S62Cw
BYwAAnqfPjOB+AP5VwH7Luly2dhrOtuyG0lmSzIBO5Ci72c8dPnQfiScAcnxUtegc7xOSSlVd3CV
l36afi/uPcf7H8q08m3u7iD5Nm7fv7YB56f8Bx/KnWNnay2rMLZB5x/fI3z5deCCT1wQee5ye9X6
qW/7m9uIeiviZOw54YAfUZPu/wCfOfIDJoLuCMx2rK6t0M8h3J64JBz7Z6H1HA84+M3xK/4Qrwg1
pYRSW+qX7SW0XmFlaJcfvJQyk/MNy4+YHLhuR10/iR8adF+Hu+1/5CetLsP9nxMV2q3OXfBC8DOO
W5XjBzXz1fXXjH47eIhLFYSXZh2oY7KB/s1qGH3m64LbCckknbgZwAN6cPtS2PqMpyuVSccViVy0
o63el+3y/BnW/s4+C57zVn114JIhA6i1uvkKqQSXYKRnOQqhunLj5sHH0bDayRpBp9hbSXHleWZV
jIQiLd8x3HA3HDDqDyT2rF8H6HYxaLoXh60Zke3gRGnhg8qRFCBnkx/D5hxzkgmTOW7+k6bpMWkm
RLb5LZsN5eMnflizlicsTlRz021nOXNK55WZYx47EzrdOnotv8zD8D2YgOoSO225cxI0PQxosYCj
afmUfeA3ckKDz1PVVFHbRRzSypEiSy48yRVAZ8DAye+KlqDzAooooAKKKKACiiigAooooAKKKKAC
iiigAooooAKKKKACiiigAooooA4uedbdQSCzE4VF6sfQf59+lQpbm4ZZbhASpzHE2CI/f3b37dB3
JfBbsrGWVxLMRjcF2hR6AZOPfnn8ABPQAUUUUAVXRrNmkjUtExzJGoyQe7KP5jv1HP3rCOsiqysG
VhkMpyCPWnVRul+w5mtkXzJGwYPuiVj+HDe/oDnpkAFuaZYYy7nCj2z9AB3PtVRdmpSOsy/ukxi3
kXG7PRmB7eg9jnkYWWGzCyCWZvPnHR2UDZ6hR2H6+pOKfcWqXG0ksjr92RDhh/iOnB4OBkUATUVB
BOxYxSgLMBnjo4/vD+o7fkTPQAVQ1TMclnOkQlkjmwFBAZgylSF/PP0X2qzcXSW+0EM7t92NBlj/
AIDpyeBkZNV7fzFvnFxtaV03RleirkBlH0O0k8ZyOOOAC9RRRQBU1T/j2T/rvD/6MWrdVNU/49k/
67w/+jFpqoupFmkUPag4RCMrJx94+oz0HTjPPGACTUZnt9PupYztdImZTjoQCRU0MS28KRRjaiKF
UegHArM1C2gs/s2Hkijadc/OzIoXL42nIA+XtjH0BFaiOsiqysGVhkMpyCPWgBJoY7iMxyosiHqr
jIP4VX+zz23/AB7y+an/ADyuGJ/J+SPx3egxVuoL6drazmlQAyKp2Ke7dh+JwPxoAh0pjLbtOylW
mkZznHIzhenH3QvTr1q1NDHcRmOVFkQ9VcZB/Ckt4FtbeKFSSsahAW64AxUlAHm3xB+DmkePNWtL
m5uL1bqGHyisUwH7vJK7mZWx8xbHBJyR0HHlWvfs138F9L/ZmrWq2m1nCanvjmUAk7RsVlkwoBLK
R1PyivpO2/d395H13bJs/Ubcf+OZ/Gm3yLdTW9q6ho2JkkVhwyrjj/voqfwP0Okako7M9nC5vjMJ
FQpz0XR6nzOn7LvitlUm+0dCRkq08uR7cR1rXH7Kt7Do8s6a8lxqKQF1s47XCvKFz5YkaQcFuNxA
9SB0r6E+zz23/HvL5qf88rhifyfkj8d3oMVHca1b2cLvcB7dlGfLkHzN7L2bt0PGecVXtpnZLiHM
Ha0kvkj5p/Zw8er4d8STaJeziPT9SGY2kfCRzqODywA3DKngkkRivpRrWXUvKknfZbN8zWjRjkdV
3HqDnkjp29Sfmr9oTwLLpesDxPbwLDp+pSmOVcBCk4LYOzAOHRQ2eSW3k4yM+6/CXxt/wnngmy1C
Vt19F/o15xj98oGW+6B8wKvgDA3Y7VVRcyU0dGc0oYqnDMqO0tJLs/60+7udHqEMaTW11sUyxyqu
7HzENlMZ9Bvz+FXqqar/AMeEuP8AWceX/wBdMjZ/49jrx60qXyqyxzqbeRjgbvusf9luhz2HB9q5
z5InmiW4heKQbkdSrD1B4NUNtz9qNvPcEW7AGORQBJJ13KSBgY9gDjkHg1oO6xqzMwVVGSzHAA9a
oWsMGrQi6mSO4STmNXAYRr6fXOc+/HOBQB4h+0/rllZ6bpfh2CP/AEmWf+0ZW3N8qhWjUnI5LEtz
nI2cj5s10/wB8Py6R4Ht5o5QLicm5eGRldf3mMEFfuho0i65IO/I7DmP2kPhvd3Jh8TabFG1pa26
wXVvEgVo1DsRLx94fPg9xgHkZ27f7P3xUj8RaWvh/Vbpf7Zts/Zyy7TcQgZ65+aRfmzwCRg8kMa6
H/DVj7GrBzyWCw2qTvPun/l/wGXP2iNSC/De5tp4zbzSzReXudSshVwSF5yeOeg4BrN/Zluoo/h/
qMUscjhtSkyFhd1IMUQwcAj8Ky/2p9QljstDtk8p7O8Zp94yW3RAhcHOMETn8h079p8CdLbRPhrp
iQWqfa7oveXBab5SXPyHI3YYxiP5QOMc4J5W1L1MGlRyNX3nO6+Wn6HZLqktjI63UTQ2qYIeVgz7
TxngnOGwO5+dSffz74/69F4T8PpdWUqxazeSiFds5WRU2HMqgHOV2qARjBYE+leiFobi2vrrU/Ji
to1ZGZ5P3aRpy7FiBjkHJ4+4PTNfKmoRXHxo+L0WnWFw8sF1cfZbe4kwzLbJkmUhtpOEDvtOD/CO
1TTjzO72RyZNg44mu6tX+HDV9tOn6+iNr4G/Ab/haPm6jqV81lo0LMjR24IuZWx8pUspQJnd83Jy
hGBnI+pvhXoekeHvCttaaXFYxSbA84tNu4k52+YRyWC8Zbng1u+GfDtl4R8P6fo2npss7KFYUyFD
Ngcs20AFmOWJxyST3rkHOpaHNqt7aRXMUYu3muC1upDLvbBGVBdcDnDDG7I74U5uTMcyzKrj6ru/
cWy/rqegiNBI0gRRIwClsckDOBn2yfzNOrF8MXi6taHUmtpre5nSNJfNDBX2rkFASfk+Y4x15rar
M8YKKKKACiiigAooooAKKKKACiiigAooooAKKKKACiiigAooooAKKKKACiiigDhOdP6sz2vdnYs0
fuSeSvuen0+7boqp5P2D5oE/0f8AihQfd/2lH8x36jnggFuimo6yKrKwZWGQynII9arec19xbS7Y
e9wmDn2XOQfc9O3XOAB013+8MMAWacfeXdgJ7scHHtxk/TJEenIskf2h1DXJLI8mO4YgqvouRwPx
POatQxLBGEQYUfj9ST3PvVeH9zqM6dplEy+5ACt+AAT8z+ABbooooAjngW4UAkqwOVdeqn1H+fbp
Vb7RPGxtwgnmABDltoK88tgcHjHA57d9sk10TIYYBvm7sQdie5Pr0+XOTkdBzUsEC26kAlmJyzt1
Y+p/z7dKAG29v5O5mbzJX+++MZ9AB2A7D+ZJJraksslxZrG6RfMzLIyFvnA4XGR1Xf8Al2OKv1U1
L93HDN3hlVvYA/KxPsFYn8KAD7Rdrw1orE/dMcwKj/eyAQPoD3/E+0XUfzTWqlO5gkLsPfBUcfTJ
9qt1VvJHZoreJzHJIcl1AJVBjJ5GO4H/AALPagCDUpobqzhUlTFLKuTIMKAp3sGz04Rhg9+tTpqV
tIyqsoIY4V8HYx9A3Qn2B7H0pIdJtIWDCBXdW3B5MuwOc8Fskc8/UmrLosisrKGVhgqwyCPSgCnD
KLzUPNQN5UURUOVIV9xB4J6gbByMg7qkewQM0kJMEpO7Kk7S3qy5wc9z19xxTNKRVt2ZFCRvIxRV
GFC5wCo9CAG9ySe9XaAKEl1dRskTrFGzHAnO5k9uOxJ7Fh1GC3SpP7Mhk5n3XZ/6bncv12/dB9wP
61Df6hEsjWrPDESvzPckbMHttJBb+XXnIxTre8t7aFIlW5KqMDNtJ/8AE8fQcDtQAsqTWCh4TJcR
7gDA3zNyQPlYnPfJ3Z6dqf8A2h5fM1tNbp/z0cKyj67ScD3PHvR9uduY7O4kTs2FTP4MwP5ijzrx
uUtY1XsJZsN+ICkfrQBWa4+0ahG1lNC/mRMHkzvUbSuOAevznuPvZ7AVbt7V0maaaXzZSu3hdqqP
9kckZ4zyc4HoKr2Mckl/czTtG8sWIFaOMrxgOe5z1H0x7mtGgArJ8Qs0cNvKx/0VJV85csMAkYYF
SDkHtz1z2rWrKtLe31hnvZALmFiUgWRcqqjgnaR1LA89cY6dKAMX4jaJJq3gbWtOMTagk9uywxM+
JBMOYQCMbhvCdT2OS2cV8wfDn4nap8K76+SCxgnW5kjW6hulZZAIy2VUg/KfmYcg4OOK+w9U/wCP
ZP8ArvD/AOjFrN8XeCtH8caW9lq1ok4Kssc4UCaAnB3RtjKnKr7HGCCOK1hNRXK1ofQZbmVPDU5Y
bEw5qcnr5f1p2Od+HfxB0z4hqdSWNbe5Tahhkcb7d8EbM5G4NklTgZ+bumB3rosisrKGVhgqwyCP
Svjmx1DxH8DfGU1pcxHaSv2m13HyL2ENkFTjoecNjIywI+8tei+Mv2oXivLdPC9lDNb+UHmm1KNs
7yAdiqrDG3kE5OTnHABa5Unf3djsxWQ1ZV19TXNTlqnfb1f5d/vPataWz0fTJruS6j0+3h2v++lW
ODcGGwHdwoLY6EZJryPxZ+0jpGm61JDpOkyakiqN99Hd/Zwz+gARg4XgZPBOcAjk+WaX4N8a/F7U
kv5fPuhMSBqF+5WELuYkJx9wNuGEBCkgYGRXrvw//Z3sNBuI9T1G8s/EEvlYW1kt91srkYbksd/c
AleOu3OMHLCHxO5q8DluXJ/XKntJ/wAqvv8AL9behjWf7VxVkW58OFo9wBkjvRuC+uPLALdfQH2r
xTWbrTrfWku/Dr3tpCpWWMT4WSCQHPysrEkAgEHgjOOcbj9Ual8KfCd1I76p4YtYYFlBR7N/JRN2
0HcUZCRkdCvy84615V4q/Z4eSNZ/CNxJeFUBlsNRmjW4bO0h0IAUrtbkNjG08knAuEqaemh6OWZh
lVOpaknTctHd3i/vb/Q5j4ofESHx5ovhoAgXdmswniVCqxbhEAq5zkZRsHJOCM80zSvjR450PTdP
SDUSNMtwLeBZLOIxsI1X93u2ZOFK55zhhzzXGapouoaHcLBqVjc6fOy71iuoWiYqSRkBgDjIPPsa
9v8Ag74p03XtDfQpoBb3VvaPFJEqxiKeM/KGBboSzKHXqQXOcFgNJWjHa6PVxkKGAwUeSiqtOLe9
tE23dad3b0OK8RfGjxR4ysY9Gth9jjvF8me1sVLG5dmwAucuARtBUMdxL5zuwPVv2b/BNx4D1ddT
1gfZNR1GMWy2cyMHihbDBs5xuZwg24JUA5x8wHaSeB9L8JLPfaNpsNpMyMrzwQoJIkIzhcAcEgAn
JIHPNWrKaG2ZZ9YacsAYo2uAzKxGVk24G0jkKeSSQScZxXNKorcsVY+MxebQnQeFwlL2cHv3f9f8
DY9Wt7mK8hWWCVJom6SRsGU844IqWsDwK0Unhizljh8ppNzSHO4u4YhnJ7kkZ9unat+sT5sKKKas
iSM6qysyHawBztOAcH04IP40AOooooAKKKKACiiigAooooAKKKKACiiigAooooAKKKKACiiigAoo
ooAKKKKAOPrKutZjmK21lMHuZW2K6ruVeAWbPQ4HOM9cVY1KV2VbWFilxcAhXAJCKPvNx0wDx7kV
Zt4FtbeKFSSsahAW64AxQBSksfs8eAZJrctumizktnJJ+hJyVHB7dw16GaO4jEkTrIh6MhyD+NPq
tNC8UhmhGWP34+m/3Ho3v36HsQAWaqah+68m4HHlON3b5G+VsnsBkMf938anguI7lS0ThwDg+oPo
R2PsaWaJbiF4pBuR1KsPUHg0APoqhb30hhSIxvNdqNknG1Qw4JJ6AHrgc4IOKk+xyXHN1JuX/njH
kJ9D3buOeD/doAg+1rHqU/lI9wHVQVhGQHUkEMeFDYK9Tn5fpm9bzrcwpKoIDD7rdQe4PuDwfpUV
1vt7Jvs67SijCovIUdQo9cZwOmcU6xgitrOGKAgwqo2sMcj149ev40AT1HcQLdW8sLEhZFKEr1wR
ipKjnnW3UEgsxOFRerH0H+ffpQAyxna4tY3cASYw4XoHHDD8CDUY/eas2f8AljANv/A2Oc/98D8z
UA0tpopC7vCzMZIo92RExO7JAPzHd82DkDoOOSun3H2q8kl27C1vEWTOdp3SZU+4OR+FAGjTXdY1
ZmYKqjJZjgAetRT3awsEVHmlIyI4xk49STwO/UjODiqGoyXhjSCSGNo7pvJby25jB4PX7xxk8AYx
zmgB2n6VB9ihYxNbyuu9xEzRHJ5IO0jgZwAegqWdptNUOrPcw52lZCB5Y7NuxnaO5OTjnsc36a6L
IrKyhlYYKsMgj0oAitIGhV2cgyyMXcr0z0A/AAD3xmp6pQKLO8aEZSB1UxKSSNw3bgPTjbhenBwO
DU9xdJb7QQzu33Y0GWP+A6cngZGTQBNRVT7VcycR2TIfWeRVX/x0sc/hR5170+zQ57nzzt/D5M5/
D0684AK1jcTxpMfsrTBp5MPG67jhyPm3EdgAME8DtVn+0o14ljmgI+9viJVfcsMrj3zxRpH/ACCb
L/rgn/oIq3QBVXVLJgxF3AQoySJF4GcZPPqR+dV/D9vBb6XGIAMEneytkM4+UsPYleKt3lnFf27w
zIGVgcHAJU4xkZ6Hmo9PZ41kt5HaV4WwHk+86kZBP6rnuVNABqny2LydomWZvojBjj3wDVuqGtNJ
JYyW0Ch7idWRVPTGOSfTjjPqRVn7XD9mW4MirAyhhI52jB6dfrQBxnxZ+G+m/ELQ4zfXv9lTaful
jv25SJDgyb1JAKkKDnIxtBzjIPy/4X1/RvA/iuS9Nm/iSK1b/RJvM+yruH/LTaVc/wC70I4PDYx6
F+1B4lnvNe0nSI5D/Z8Vt9rAAYCSRmZdxzwwAT5SB/E3PNdN8Hfhf4a03R4dT1mFNRu9Qto5o/7T
tlEEaMqsVQMSGOSPnPOMYA+bPVF8kPe6n3uEqRy/LVLFTcoz2itOuuu/4pb6M85139oLxBqm9bO0
0/TV80ukog+0T7OcI7y7g3BHIUdBjA4rM/4Vh8QPE1s1/c6XqEyW6mPdqUwjdVHzEBZWDbfmJ4GM
k9819caNoGkaIsjaTptlYLOFLtZwJGJAM7SdoGepx9TVy8ZVtJjI7RIEbdIn3lGOSPep9qo/CjgW
eUsNpgsPGPm9X+FvzZ8j6l8FfiLqVxLe6hpst1cMMyXFzqELsQBjJZpM8ADr2FJN4u+I3wz1yCbV
LrUklZcLHqjtcQzJ8jsqliR/dBKEMM4yDX1bY2byRw/aAhigIMEYjK4wMBmBJOeuB2789OX+L3iS
x0HwdeS3cMN4iso+y3EavHLJ1jRg2Aw3hGKg7toYjpTVVydmjSjntXFVI0K1CMk9LJd/W55PP+1B
JqFiLW+8NRTwyQ+XcpHd7VmyMOMNG2EIJ+Xk/wC1Unw5+NzrrWk+HdI8IwjSzcqlrZJcyStGjhxN
vZgd4+dmzhQoBzkV5x4R8N2/iCz8SeI9UmhisdIiE8lukRUXE8hYQxBYwNkZcYO3GAcDbncrPhNq
sGj/ABE0We5TzIHla2YZIH71GiBJHOAXycAnAOK1cI2dkfQ1stwMaNaNKnrFXteVua1113/R+bPr
/TV0x5LpdIhMxNustzYqGkIxwyo5OHwSOMc7sgn7tbuheF5Gs0F62LOeHc9iN6qGb5iuxmIXaecr
g59MHdnN4Di1CEXNzNY2dqBvBtFyPL+UlvMyo6A9VIAOee3Sv4kt21TTrW2aK7jvDKpmilDBCihs
cZznI7iuE/LDP0Nbvw3fQaPJHv01mkW1n2fMxwZPmIbHHzjoM4BHGcdRWJb65cah4ga0tIUNjbqf
tM8h+YtllCoPZlbJPofYmDR9X1CbxFc2l9F9nWS3WeK3ZlZogNqtyowQzFsc5+XoMigDdkuYovM3
yonlp5j7mA2rz8x9BwefY021kt7iMz2zRSRyncZIiCHI+XOR16AfhWFrPhM6trSX0gt5lWNY0WZW
2x4O7JUH95kkjBKgDs1dFHGkMaxxoqRqAqqowAB0AFADqKKKACiiigAooooAKKKKACiiigAooooA
KKKKACiiigAooooAKKKKACiiigDzXTZ0ilae6JkuZSkYmWOQoVwoGG2gAFsnjjkVtUyaGO4jMcqL
Ih6q4yD+FZk2mSWs0Z06GNG8h4zJI/Izt25OCWxg4B4wKALj3x3MIreW4VTgvGVAyOo+ZhnHt9Oo
NJ5l9/z7W/8A4EN/8RRp8hCNAYliFvtjARy6/dBAyQDnBHbuOeuLdAGVeLexslyHghfckZRUZ8hm
C8tkZwTnoMdO5za+y3MnMl6yH0gjVV/8eDHP40av/wAgm9/64P8A+gmrdAFFdNdJHdb64DPjdxHz
jvjZ19/YelS6fM81nGZDulXKO2OrKSrEe2Qas1mwvcw3F3DDFE0ayb1EkpU4YAk42nILbufqO1AG
lWdDdw6fM9pLIsZ3jyUJ5Kt0AHoG3DHYAfWpv9Ok/wCfe3x/vS5/9Bx+tVr2O72xLLNCYWlQMyQk
MvPykfMed20dCOeeM0AXZ7hlYRxIJZiM7S20KPUnBx7cc/gSCC1EbGR2MszDBc5wPZR/COnT0Gcn
mnwW8dspWJAgJyfUn1J7n3NSUAFZS2CrqtwDLKizqHCRttBAPI45GC27gjO/61Y1jWLLw/pdxqOo
3CWllbrvkmk6AfzJJwABySQBya4Xwb8aPD/j7xBBZ2AurW9CsFivUVfNQqWYptZskFF4OOCcA4JF
craujphhq1SnKrCDcY7vsegWtjb2QYQQpFuOTtGM8k/1P0pbq3+0RgBtjqwdHxnBH9Ox9QSKmoqT
mIbO4+1WkM23b5iK+3OcZGcUya/it5vKbzGfaGIjid8A5A6A+h/KsHXPFVn4M0+ebU7qHT7dJSTc
TBnz5jsVCIvzOeGyOMYJ5ArhJP2jPBmj3lxHAmqakWYM17HAgEvH+2ysAM4xtA449TSjKWyO2hgs
TiVejTbXe2n3nqk1w91GU+wzMjfdZ2VB7H725ex6ZHpmjTV8rfHKii8Cq00i8+ZnOGzjpweO2MdM
V5/pf7RngnULdpJ7y50xw20Q3Vq7MRgfMPLDjHOOueDx0q03xw8D308CQa/GlyXVY3lt5o05IyrM
UwqnuTwOvanyS7GksuxkW06MvuZ6JUN5cfZbSabbu8tGfbnGcDOKwYfiR4UljDf8JJpKHur30QI9
vvf/AFqktvEui+KL5bDTtXsr8ovnypZ3SO20EBfunI+Yg5HTAB+8KmzOSVGrFXcGl6G1Z2/2W0hg
3bvLRU3YxnAxmpqqf6Va/wDT5H+CyD+Sn/x3AHevJvFX7Teg6PcS22k2U+tSxyBDNvEMDLjkq2GY
4OB90A8kHGMuMXLY2w2Dr4yThQjzNHsM0ywxl3OFHtn6ADufaqC2c91N9oM726SEhowuGaMfdGeq
/wATevzY7CvmXWv2jPFuvXEcOmwWumt9o3W/2aEyzchlVDvyrHDdQoJI4x0rPk1D4r+Iprq+WTxK
xVQ0n2YSwJxtXCom1SeQSFGerHua19i+rPejw9XX8epGHq9f6+Z9Tavcab4Z0m81GeWHS7eGIl7g
r8sfuF7knAwOWIUc8V5c37RXgjS51WCwv7lo1XFxBboRyoyA0jq/GdvIHTjjFeXWnwf+Injy4trr
UobkB1KLd61cndGqljgqxMgGc4G3+LPQ5r0fR/gJ4e8L6fGuu2r6/qM8O8hLh4Yo2XcZAu0qcbSv
JyTtzhc4p8sI/E7mjwWV4GN8TV9pLtG2n9eq9DzSHT9d/aD+IVzdJH9kt/lEkjFnisoBwqjPVjgn
aMbmLHCjJH1e6nU1ZQxW0YYJXGZQev0XHccnqMDk5nhvwvpeg6Wun6PZpZaSGL7FJYzsepZiSWXo
Mk8gAfdAz5J+1dqFxHp/hyxWTFrNLPNJHgcugQKc9eBI/wCfsKTftJKK0RjUq/21iqWFpLkpq6j5
K19fu7/5ns1qr6KYbUrF9kkmZIn3kMuQWCkEc85Gc+lXL5Ua33M/l7GDKcbhuB4G3+Lnt1zjHODX
yv4a+PV14V8A2nh6y0mNrq2YtHfSzkrkzGTmMKPXH3vf2qpqP7QvjS+kheO9t7Not2PItkOc45Ic
NyOeRjqfWj2Mrlf6t41zcVa13Zt7rvZX3Pq/+0h9nJ8si6AA+znIJcg/KDjkZB+YccE9jXzH8ePi
XaeJ5LXQNJn+1afYytLcXa42XNwcjcnGdo3PyDg7zgYCk4Gg+D/GPxq1Sa/Mr3gVjHJqF/KVhiJ3
PsXgnGT91FIXcOADWNo+krofxEt7DU40uoNN1HbfCOJpozFDJmZtu3LIFRyeOgPFawpqLu3dnuZd
lNDBVnUnUU6kFflXT+um3fsd78TtHu/hv8LfDHhoHypNTllvtT2sctMojxGcMVKruUccExqwxXnO
ixt4b8XaNLqLPZxxT2t28kfzskTbJVcAHk7GDYzntwa6rxt4r1D44ePrG1sIHhgZha2Nu5Ztik5a
WQDIBx8zFRwqjrtyfSPix8IbCfwtp8mnFpde0ywSF5YYsLepCgQhlBP7wBeMZIA2txgrXNypKXU7
YYqOCp06GNdp1eZy8m3p/l8uyPW7nWtN1TwhFp+lNdnzCJbXeqFLkMxZsFMoVAYntghfSuv0661H
UjA9tbw6fozRAR7seftKZVlAyijJHBz0P0r5M/Z98dRWurR+HtYY3VhKT9jhkuDHsdzh40Ixy+cg
FgpIYAbnr7H026tbu1U2ZAhT92ECFNmB93aQCOMcY6EVyTi4Ox+fZhgZ5fXdGWq6PujPs/C8NjDD
HBe3qBLg3MjeaN07kj/WHHI4xgYz3yeazpvEjahqF7Do2medqtruhkuLlVVFVSfl3A5OSOBx1z2N
aPiS8jj+x2Ms72y30vkiaCYpMjdQVGDkEgKTxjcPWjStPi8K2drZRvD5DyuDNM4jdmYkoAMYdsYH
Ufd49Kg805rVta8VR2/2kRra26RLJ8kIV2LttVSG3/MDzgdjzgkCu6triO8t4p4m3xSoHRsEZUjI
PNYPiy5lt9J1D7bDnTzt8ua2c+bG3y7WKkqDh+eG9OOprK8F+JLe1aHSrg+S0yia3yAqgvyYwOo5
JK56hh22lgDuKKKKACiiigAooooAKKKKACiiigAooooAKKKKACiiigAooooAKKKKACiiigDiLe8i
umdU3hkAJWSNkODnB5A9D+VT1Qvle1uFvkwUVdk6knmPOdw915PTkE1foAqW/wDotwbb7yyb5kbu
PmBYH8W49vpk26zmaZtRllgRSkSiKVWPzSHAYBewwGPOeScHHBDLzWJLPyM2E372VYhudB19MMef
rge9AGjNEtxC8Ug3I6lWHqDwah06Z7jT7WWQ7neJWY46kgE1XuPM1DyoJLORIGcNIZChGByBgMep
Cjp0JqbSvlsIo/8AnjmHPrsJXP44z+NAFuqn+r1b186D8tjf18z9PerdVLv5byxccMztGT/slGYj
81X8qALdQ3dv9qtpIt2wsuFfGdp7MPcHB/CpqKAIbW4+026yFdjchlznawOGGe+CCKmrNjvIrW8n
Rd8sLHcTDG0gR+jKdo4zwcdclieoqV9RZVZ0srmSMDO5VUE/8BYhv0oA8Z+Onw08U+PvGGltpVv5
2lx2qxGSW5VYoZDI29tpO77uzJVSSAOuMV5J5Op/BL4mRSTWxmk0+Zmi80bFuoGDJvUjONyk+u05
B5BFfZiOsiqysGVhkMpyCPWvG/2k/CN94m0rSLnTIpb67sZHD2VtGZJDHIF/eYBzgGMDgH72eMV0
06n2XsfZZTmzk4YGul7Jpx7b9/Xbpues6LqkWuaPY6lArpBeQR3EayABgrqGAOCRnB9a5fxJ8ZPC
XhvS2vG1i21I7gi22mzxzzMT7BsAAZOSQOMdSAfm6TT/AIla5pdj4blsdefT4QsUdrJbSRxhSw2i
RiACoKjBc4ULxgCuz0L9lfUrzT0m1XWodMumwfs0MH2jaCAcM25RuByCBkccE5pezjH4mJ5TgcK+
fF4hWvolrp+L/D5nIa9r3iD49+MLaGG2jgESMsUKu3k20O4lpZGJIBwVDMAM7VAGcCva/Dv7N/g/
T7UG9W41uWREzLNO0aAgclBGRgNnoxbGBz1z2PhD4b+H/A9r5Ol2Cq7bDJcTHzJZGUYDEnoepwuB
knAFaWn3yQ2cduiSTyw5h2xr12Erkk/KCQM4J7jrxmZVOkdEceNzicrUcFenTjtbRv8Ar/hzy/U/
2Z/CS+fcR3OrRBmJjt47iPaCxwqAtGTjJAySfc1naj+ynpskcIsNfurZxu81riBZg3TbtAKbcc5y
Tn2r2R7pLy8toAGR0YyyRyDHCjA+vzMpBHHynB4rRqfaT7nHHOMfB3VV/g/zPmWw/ZY11ml+3avY
QRrGWT7KHmZn4wpDBAAeec+nHpma5+znr2ntMdPvbTUApURQzE208pOAQA/yHBJ6SHIHqQK+raa6
LIrKyhlYYKsMgj0qvbTO1cRY9S5nJNdrK3+f4nybeeE/i34b0+AZ19LVNsMcNjftNsAHACROxVQB
jpgcD0rpvgz8CZrwyax4osPJiXi0sLyNg5dXB8yRMj5flK7GHzBieBgn3m1vWsbG1gktZzKipEwA
UANjA+YkA59j6A4JxVrdfPx5dvD/ALfmNJj/AIDtXP503VbVgrZ9iKlGVOEVBvdx0Zj6P4ds7OC4
TT9N03SYZm8u4+x2yoZwjFTnaBt/ix97G49K2rixiuJlmO6OdV2rLGxVgOuPcZ7HIqLTRJA1xbys
rOrmQFVK5VyTnGT/ABbh+FXqwPm5SlJ3k7soW+oeTIbe7zDKoZlkkwFkQE8gg4zjBI469MVW1O6s
b5beP7TFN++UGKOYZYNlCODn+LP4YqfXJIzYyWxXzZrhTHFEBks2Ov0HXPbFaNBJkvZ3+m28hs7h
rw8ERXfzNnPOGyMDHb296xfGnhex8a6dEmsaJFKtqGmElzMV8o4G4KYjuII7cA7QcZArsKqal+8j
hh7zSqvsQPmYH2KqR+NO9ti4VJ05KcHZrqjiPDvwb8H2Fq0Mmhwyz8NIl3+9ZGI/hJydpxxyRwe+
a7VNItYdLj0+3iFraxqqRpB8nlhfu7cdMECp7i1juNpYYkX7ki/eT3B/yD3ryv4lfHy38C3lzo9v
YNf65Cqh2Y7LePcm5T/eY8oSowMEjdkVS5pux20qeKzGp7OLc5b6v8dT0e/1oaLay3OohYbSFHeS
4TLcIjOzbQCcbVPqc8YPWvh+8mvvF/iK6uI7VrjUNQuJJzb2kbMS7sWIVeTjk+vFdD4q+KXjDxZA
Jb/UbiLT5HmjSK1XyYDkDfHlcbwFZRhixAbn7xz6l+zL4B8tZ/Fd4kbb1a3sRuVivJEjkYyp42jk
HBfIwQT0xj7KLbPtsLh/7AwtTE1mnJ2SS766f5+h13wZ+D6eBtJlutXjhudYvVXzI2RXW2UZIjVs
ck5yxBwSABnbk91No2lWkpf7OBNKGCxo5y+RghRnHQ/Qe1bFUbeZTqVwqHzQygl1GQjLwUJ6DsQv
XJY9xXLKTk7s+CxOIqYurKtVd2z5r+OHwdXwrD/wkWlqU0+ebbcWYT/j2Zs4YFRtCE8Y4CkqBkEY
7j4MfEC98SeF5rcJfy6hYsPtMtveSAyBhhJCMHLHBzySShJ4OK6D48X8U/wp1xE8xs+RhvKfYf38
fIbGMe+a8t+Bfjzw34L8P6muoapHpepXVxy7W007NEqDZgKNowzSe5zzwBW+s6fmfWXqZllDc4uc
4Ssravpv8n+R7npV8upalczXOpLaqJ45DNGPMkmKuNuFZdxJ4xtGF2nKDNXdU8UTeItae3gsIpYL
ZJlUSxI7M2Cqv+8A2jdsO3r1znpXz7rvx9k0fWC3hlFukVnEt5qEZxcDIxtQHKjgnJOTuHC4OV0r
9pDVHuNQu7+3tLa4+zfuBaQsUllB+VZFZzkc8tuBCqcZJAqPZTtex5SyHHumqnJ8uv3Hs/iH4iaT
4TeLRta8SWIsPJW3nt5Y/Mmi4UghIkLKduCpbI9T0rg1+LfhLzg7avCT5SfPJbXEpXaoUqAUwTgd
DwOACMV5b8NPhbqXxY1DULme8mtLVMvLqUsXneZOSDs5ZSzEEsTk44z94V65d/sv+GIbaSSK+1h3
RdwTzYjuxzgfuup6f41ThTjo2d9bL8qwcvZYirJzW9rf5P8AM09K+LHgK4e0Da+sF80yyRkW8sUU
EhK9NybABgAs3pkmuv8ACfxmg1S8+zPe2d9FH+8llt5UeVI87clVPOGZBkDpngk15jqn7K+kXSwN
pOvXdsuCXa6jS4Dg42lduzHf1zkdO/j2uaLqHwh+IAglP2h7N1kjmCFFuIWHUbgcZBZTjOGDAE4z
QoQl8L1HTyvL8cnHBVXzpN2a/wCAv1Pu0+JrceJF0YqwnMZcPkEE4BC4Gccbj82Og65FbFeReF/E
2j6oyXek+IV1m5ZPOniW4JuGi27XwgIdDyuM9GVPQV6xbeWbeIxP5kWwbH3l9y44O4nn696w2Pkp
wlTfLNWfmS0UUUiAooooAKKKKACiiigAooooAKKKKACiiigAooooAKKKKAOPrKV2WF9PjYhlk8lW
U4Kx7Q2fbarBQeeduetatZJDx+IwUjZo2i+cjorNn5j+ESj0/qAXbKxjsUdIyxVmzhj0woUAewCj
3pt/aPcNbyJtcwvvEUnCscEAk4JBGcj/ACRbqpqUxjt1jUsHmdYlKA7hk/MRjoQu459qAJ7edbmF
JVBCsMjP+efqOD2qDT/la7iH3Y5zj1+YBz+rH8MVZRFjVVVQqqMBVGAB6Vnid49UuoreMSkrG7Zc
BVc5HzHkjKqvQHp2zmgDSqpqXEMTDhlniwe4y6g/oSPoTR5l9/z7W/8A4EN/8RUdxZ3t1bywtcwB
ZFKErbtnBGP79AF+q11M+5IIjtmk5DY+6oI3N9eeOvJHGM1Wuo7qIwu166q0gSTy40CgEEDAIJ+9
tHU9T07SRxmzu2aWRpVlVUEz4yCCcKcAADnjjqSM9BQBbhiW3hSKMbURQqj0A4FPoqtezOsYjiOJ
5PlTjO31bHoM5568DuKAK8EcsklwkM3lW4lPzKoLZOCwUnIxuzkkHkkcYq7Bbx2ylYkCAnJ9SfUn
ufc0sMSwRhEGFH4/Uk9z70y4uo7faGOZG+5Gv3n9gP8AIHegCJv3OqIe00RUk+qnKge5DOf+A+xq
3WSbqS8ktLnb5Vqk+3a64fJUpk88fM23GO2c4rWoAKqaf8rXcQ+7HOcevzAOf1Y/hirdUbCTzrm5
ljVlt324Zhjc4yrHB5GAFHOOlAD7j/R7tbluYtmx2P8Ayz5yD7A9z7L2BNW6a6LIrKyhlYYKsMgj
0rL1KEabaTzx300B2HaskgdWYAkD58nJ9Ae1AGtRVGF7y6hSaOa3jSRQyr5bPwenO5f5CmSLO1xD
DdSRyQS7hiOMruYDIU5Y5BAY9vu4PXBAHzF9SjMcY2QH/luwzu9CnPB7hj6AgHOavUVHPcRWqhpp
UiUnAaRgoz6c0AVL60dbqO9twWuEAjdOP3kZPI5IwR1B9qsWt0LgMCpjlQ4eNs8ckZGeqnBwe9V5
dWikkhitJoJ5pW28SA7RtJ3EDr06cdeopV0wmR3kupnMmN6qQg46AEDcAPTPr1ycgFVkmvNbkAvD
beSuFiWMbmRgpLAtn+IY6fw+9XfsU3/P/cf98x//ABFQXWlrGqz2UUSXURLhmTJkO0jBbIPOepNW
bG8F9AH2NG4wJI3Ugo2AccgeooArXqy2Fu1wb6VthB2yCMK3I+UnaMZ6Z7ZzRb3sN9qxCMQ0EJBV
1KsdxBPBAPG0f99Cp9Q+ZrSI/dknGfX5QXH6qPwzUOseZH9luYrfz3hl5AzkKylSeATjJB4B6UAV
vF2uS6D4d1a9tY0mu7SzmuVSTOwbEZgWxzgkdByfbkj5a+D/AMP3+Jnii8utTaa6sbTFxeHzf3lx
IzcIWJ3ZbDkt/skZUsGHc/Hr4p2DaVdeEdMePUJp3V9QvFOURg4cRpg8tlVB5IUDbyc7eg/Zf8Nt
pvhG+1iRXV9TnCx5ZSrRRZUMAOQd7SA5/ujjuemN4U2+59phY1csyqpiH7s5tKPe3/DXa+88p+Nl
5DqfjxND0S3xYaeq2ttZWfKedId8gSNQNrF32leTlMegH1NY6JaeGdPtoNKtVt7W0i8tbaIH5kzn
6ls5OTnJZs8tmvmXwXb22uftGN50ZeFtWvLlFYlSGTzZEPB7MqnHTjuK+sKVXRKJz55P2dPD4aOy
jf1b6+uj+8x5r62ubzy2uDcwldyx22XHGAd4UEnr34PQjjJdcXX2i3ito7OaKKZxCCyqilAfmGM5
A2Buwq2v+gzhP+XeViQx/gcnOPoxJ69+O4AnuLdLqIxyAlSQflYqcg5ByOeornPkznviXcRWvw78
SvNKkKHTrhA0jBQWaMqo57liAB3JAr5c+EPgzw7421i6s9e1h9MfagtYI3WNrh2bGA7gjI4GzGW3
ZH3TXpX7RnxBGn2cng62Zbs3KRy3UkhDNAocMiAg53HaCdwztIOTuyPLLH4N+LtT8Nwa3aaS89pM
ryLGrqJjGoBDhCQSGydoGScdMFSeymrQ1drn6Jk9F4fASdWp7N1Ho9P176/I+hPAvwM8L+F74amk
VxqF5DOxge+kDCEozKGVVVQT0OWBwQCMGuc8bfs16bqery6hpepf2NbzugayW28xEdnAJT512rzn
bjjnGBgDP/Z5+LF9qWpHwxrNw120qyTWd1MzNKXGXeNjg7gRuYMx4wRk5UD3W++aSzjP3HnG4eu1
WYfqoP4VjJzhLVnz+KxGY5bimp1XzW33TXo9P+Dco+E/Cem+CdDh0vS4PKt4+WZuXlc9Xc92OP0A
GAABs013WNWZmCqoyWY4AHrVbzprz/UFY4D/AMtiMs3+6OmPRjnp0Iway3PnpzlUk5zd2xkMn9nR
i3dWYLxBsGdw7J9QOOewznrjjviR8JbP4mWcb3cq6dqsOFhu4U8zamclGztLg5JHI2np/Fu7H+xb
RpvNmi+0y7dpecl/foeBz6AU/wCweTzaSfZv+meN0f8A3z27/dI565oTcXdGlGvUw9RVaTtJHyl4
6+CPiL4cyR6nYzPqdlC3mLe2KMk1uVUNvdRkoAQ2GBIG3JKkgV6t8F/jtd66bizu7aOK9tbX7RcS
ov7u8IdVLbRjy5DuUZAYHJJACqK9Tur65hsboxWYn1COF5IrQShROwHyqHIwMnAJI4zzxjPy18Ef
BeoXPxQltpk+zNpKXC3eSTsba0O0FeCdzdM4IVuTXRze0i+bofXxxKzbAVZYtLnpq6fX7vuXbXuj
7X0bUl1jS7a9VPLEybtm4Ng9CMj/APX6gHirtYnguJLfwzZRIHXYGVxJjIcOwfp23Zx7YrbrmPiQ
ooooAKKKKACiiigAooooAKKKKACiiigAooooAKKKKAOE+3O3MdncSJ2bCpn8GYH8xVW4lvIbhLr7
PEqkCIoZiGO51ClsKRxk9z94499Wqmqf8eyf9d4f/Ri0ARvdS2M0f2yeAW7gjzAhTD8EAkseo3fl
71DDZrqgd7ozv5cxMasGiC85UqAAehAye4OPfVooAqf2Vat/rIvP9PtDGXH03E4/Cm6WiwwSQqoT
y5pBtUYCgsWUf98sPzqS6unhkijji8ySTO0s21BjnBPPOM4AB6H60WdvJD5zyspeZ95CA4X5QMZ7
9OvH0FAFmiiigCpqnFmXP3Y3jkY+iq4Zj+QNT3EC3MLxMSAw+8vUHsR7g8j6VFqMT3Gn3UUY3O8T
Ko9SQQKmhmW4hSWM7kdQynHUHkUAV/tFzD8slu1wf+ekG1VP4M2Qfz/oKOm6l9q1K9eaNoBCgVfM
HCgMwY7s45IGf93vtzWzWTH9lbVroz/PMJUVN2WVPkUr7KdxbB65JxQBb86a74hVoI+8siYY/wC6
p5B92HYcHNS29rHb7iozI335G+8/uT/kDtU1FAEdxbpdRGOQEqSD8rFTkHIORz1FZ81otpe27WkU
cczq6NI44YcE5PVmyAeTyA3PetSqk377UYE7QqZm9iQVX8CC/wCQ/EAPLvv+fm3/APAdv/i6Zpsf
2RWtXC+avzeYFx53Ay5988HnPQ9xV6oLyBpowYyBNGd8RboGwRz7EEg/X1oAnrN1eZY59NHnCJmu
RjjJI2sCMe+QM9s1et51uIg6gjkghuoIOCPwINZ00sbTS3MoH2GRY4/NLYwQzEMP9nLDDZ6gHpzQ
Bq1WvLeS48lopFjeJ94LoWB+UrjGR/epEdrNljkYtExxHIxyQeysf5Hv0PP3rVAGdDqLpJcQzK00
sbhVMEDBWyqkc8gHJ7mrFra+XiWUK90y4eQf+gr6L7fj1yarQ3sNveX6OxMnnA+XGpdseWnOACce
9EmsP9oFvDZTvKwDAuAqBSTyx5K9DwRnjpQBbvIGnhPlkCZTvjY9Aw6Z9j0PsTT7edbmFJVBAYfd
bqD3B9weD9Kzxql35hiOmyGVXw21xs2cfMGIAJ56exziorXVkj1G7tzb3Eartcr5e/axHI+TOAeD
9S1AFrXpZIdJuGhZ0lICqYxlskgYH1zirFpZQ2KusKlQ7F23MWJY9TkmqhtRrDRy3EMsMMYDRxs5
Rt3Xcdp7DGO4y3tXAfEL4teGfBcNxaw3s+pawoZBa2l07eW/zD94+7auGXBXlhkfLimk5aI6KGHq
4mfJRi5PyPRr3/j5sP8Aruf/AEW9eQfGn44Wmi2eo+HtDuJm1riKW9tyAltz86hupkAG3gfLu+8G
XFeReK/it4m8fXUlratcWtkyyFdPspJJCUCvuLsSWb92SG6KQM7RzXZ/CL4Cwaxax674meN9MZH8
qxjlZWJDMpMjDG0DbkBTzkZIwQelUuRc89j6+jlFLLYfW8xeitaK113SffZ6bediL4MfBOXVFtfE
mu2fm6cGEltp0gG65GDiRgSBszghT94ZP3cB/fGuCqw2mmSQWdlHHCimOEHylbIQBcgAcIMY4Dds
VbsY1uLOGO1QWWnIoSGOFdhKDgADHyLgcY5xjkdK8c/aG+Ja6LYP4P0wYuLmJWvLhZeYoyc+Xwc7
nxlt38Ld9+RneVWR5EqmJz3GKF9H90V3/rc8fsvGkfhX4pXHiLTEXULaK/uJIVlynmwuXX0BUlG4
yODjIPSvrTwZ480Xx9p7XWj3XneXtE0EilZYWIyAyn8RkZUkHBODXg/w9+Aa6xoEV7rm5ZNVgD2I
gn2+SvDh2IRgWZeingKWz82NvI/D3XG+FvxOkj1C7a3t4JZtPvprVBJ8oYjI3LnaHVW4G7APHY7S
jGpe26Ppcfh8LmkZxwzbqUlb1S6efX5+R9fXskXkmGRWl81SvlICWYdD06DnqcAZHNJZzSZMFxjz
lGQR/GuBz0HQnB/A4GQKr+H7+w1jS4NS026F9bXSh1udxJcc8c/dwc/LgYORgc0WsDXu6+yIpZAp
gYclY8AhWHGckkke/XgEcZ+dyi4txkrNHynqUZ+J3x2lhCRXdtdan5RNtIAsltF8pcNnn91GWyDy
enUCvq+4hktbeWZr+5KxqXIVYs4Az/cr5Z+EOktoPx4s9MaQTNZXN5bGRRgMUilXOO2cV9TalMZo
ZbWGN53YbJAgHyqfvcnA3YPAznkHGK6K26R9XxDJRqUaMPhjBW/L8kj5M+JPh6T4U/Ey1nsxC4Vo
dUtozkopD5KEALhd6NgD+HbznNfVUGoLri2F5prpcWkkIuElcMoG9QUbGMk7WY7TjqM44rzL9pLw
zNq3geLWJPJSbS51O1WbiOQhGAOMMS3lHkDADde8/wCzHrDX3gG4spLhJHsbx0jhG3dHEwVxkDnB
cyYJ9CO3BL3oKXYrGv6/llLFt+9TfK/6+772ejag0Vn5clxeB50ZXMcjhVK55wmecckdTkDk1d/t
ENxFb3Erf3fKKfjl8D9c0SfudShfosyNGT6sPmUfl5n+cVbrnPkSG1ulvLdZUDKGz8rjDAg4II9Q
QRU1ZUkp0m8uWW3nlhnAlCwRhv3nRunTI2nn3q5uh1SxbY++CdCu5PQjB/GgDPuNSfUbJTZ2dw07
LvjZ12BD0DbjweD0GcjIPBNVb7Q9QvJY3EltDNGD/pUW5ZHOCBnHAyMeuOcelauiTvcaXbtJH5Th
djJjGCpKnjAx06dqvUAV/A3igzXP9lPF8iBgLlWLiSYsztyFAAYbiB6KetdxXmuraD51wdQs2ZNQ
jKvHyNpZSMHBHXA+nAru9D1iDXdNhu4GXDD50BzsbHKn6fr170AX6KKKACiiigAooooAKKKKACii
igAooooAKKKKACiiigDj6qap/wAeyf8AXeH/ANGLTUW+kVWFxAAwyN1swP5F+KgvpLtooxLBCief
FlkmLH/WL22j+dAGpRRRQBQ1S4S1ksZJCQonx8qljkxuAMDnqatwXEdypaJw4BwfUH0I7H2NVoXW
61KSRWDJbr5WVP8AGSCwP0AT8z+E09nHOwkwUmAwJYzhh7Z7jPY5HtQBPRVXTrg3Fv8AM4eSNmid
hjllJGSO2cZx70s2oW0MhjaZTKP+WSfM/wD3yOentQBZqppPy6dBH3iXyW+qHace2QahupLm+h8u
CCSIFlbzJJPLyoIJA25YEjjkDqfpUmm7ovOt2WJPJb5Vhj2AqQDnbk99w/A0AXajuIFuYXiYkBh9
5eoPYj3B5H0qF75WZo4FNxIpwdv3VP8AtN0GO45PtVVo7q9kuLeW48hlQMv2cEY3ZAy3UkFT0xnH
PXAALtjO1xaxu4AkxhwvQOOGH4EGp6pLpUWWZpZ3kY5ZxMybjjGSFIHQAdO1R2uoJbxmCVpJJoWK
NtRpGx/CWwDyVwc+ufQgAGjWbJJFa6k8hnFvFj98XcBXcgBRz0IUEnGDyvWp/tVxJ/qbRgOoadwi
kfhls+xAqili39qDzNsRnSSR/JZt5wUGDIfmxz0G0DpzQBs013WNWZmCqoyWY4AHrVRNNFqqizkN
uFGBG2XjP4E8d+hGTyc09LFWZZJ2NxIDkbvuqf8AZXoMdjyfegChfSJM8c1utwoaVFeaNtkbgsFO
RkZ4PDAemDxWt5Mfk+VsXytu3Zj5cdMY9Kr6p/x7J/13h/8ARi1boAoW0P2PbZSsZ4HXbEZAOgAB
Q8AHjJHqM+nML28kGpRwRyy/Z54yXDOzMu0jkMW4zuA4544x1GjPbx3KhZUDgHI9QfUHsfcVl6hp
cPn6fsyJPtKt5khLthVZtuSc446UAasMSwRhEGFH4/Uk9z71Xh+bUrpxyqpHGT/tDcxH5Mv51brw
X4zfFDxP4F8UWI0pkt9OmDTt5luHWd0fy2jLHsFjU4XaR5nXoaqMXJ2R24PCVMdVVGk1d9/I96rj
viJ4+0/4b2f9p3n7+W4QwwWaMBJM65K49FG47m5xleCTg+O6b+1Rqq2eoDUNJs5boxf6G1sHRFkz
j94GYkrg54IPy4/iyvF6PoPin41+Ivt9/PNLAq7bnVZosQ28aAEqoUBS2GyEXBJbJxktWypNay2P
ocPkM6U3Ux7Uacd9d/T+r9i34q+L3i/4mXjabYrNb2s+5U0zS1ZnlXDZDkfM/wAhIYcKdudorqfB
P7MN/fbbjxPd/wBmw/8APnaMrzH7w5flF5CnjdkEj5TXtXg3wvp/gjSYrLTNDktzsVZpsxNLMwyc
u+4Fjlm9AM4AA4re+3OvMlncRp3bCvj8FYn8hSdW2kFYmvnns4ujl8FTj36v+vm/M46bw1pnhH4c
6vHoejwW7vaSJOsRwxPzByzsSz7NzkAk8DA6itfSri2j8J6TZLdQzO1tbQkI2C6sEBwDhsFSewOD
2qzeW6a19ssYpGS2uoit1gbZI8qV4DDqwx1HAXP8QNUPh7It54TitJ4Y4rqzdrO5jiG3bJGcA5HV
toQ7gevT20vzUH5P81/wDy5VJV8DJyd5KabfXVWX3W/HXodSiiNVUZIUYG4kn8z1r5B+EXh1viV8
ThNqjpcIjPqd6HVR55Dg7du0qQzuuVwBt3YxxX0v46mdfh/4lgmOZ10q5+bGBIPKb5h/UdifTBPj
P7KelxTax4g1Is4nt4IrdFBG0rIzMxPGc5iXHPc/hFP3YSZ6mVyeHy/FYiL10S8v6ufRF5ai6jAD
GORDujkGflbBAOO/XoeDXnvj74SaN8QtPm1OS0eHxAISPOtJBGZZEVlEb7sqRuwN3XCgbsCvRbid
bW3lmYErGpcheuAM1UtJF02xgS5c/aHBdlxuZnJ3NgKOcEnoOlYKTi7o+cw+Iq4WoqtJ2a/q3ocv
8HdSGoeBbSIGQtZu1sxfpwdyhefuhWUD0xjoK6aK6SzuLm3IZnL+ZFEg3MVYZJ9hv3cngZHQYrnv
C/jKfxnoct+lsunwRXIgkXzDIxX5CzbsLtADHnnv0xmuugt47ZSsSBATk+pPqT3PuaqfxM6cy5vr
lXnhyNttq97X13R8l6peN4B+P1zeXrpHEuptPMwLny4Z/mY/Jg7ljlPTPI/iHX6jaSbSYbsRWgNv
EWlT5wqhdoLAYyc7t3BGPfpXgP7VGhWlnrmi6rCmy6vopYp9oADeXs2scDJbD4ySeFUcYr3L4d/8
k/8ADP8A2C7X/wBFLWlT3oxkezm3LiMHhsWt2uV/L/g3H+ONJ/4STwTrVjBBHey3VlKsEbbSrSFC
YyCeAd20g9iAa+fP2YvE8ek+Lr7SZ3jjj1OAGMsp3NNGSVUEcAFWkPPUgAHsfozS3vJNMtFjjiiT
yUAkkYsfujnaB3/3u/4V8na6D8NfjTcSSBEgs9RFw0dggUC3kIfYinG0+W+3GeD0PANOn70XEvJl
9aw2IwXVq69V/wAGx9d3v/HzYf8AXc/+i3q3WLDfS6lptpNBC90rGOWO6iaPbKmQd6/NxuTPH+1i
rJk1C6YRiJbJQ3zzbw5IyfuDHfA5bHXpXOfJbaM0a5+zup9Pmvlis5buGS5cpKnHznGVIPRQQRu6
cVYtNNXUIC1/K94wZ48N8qDazLkKMDOO5ya1Le3S1iEcYIUEn5mLHJOScnnqaBGXYPe6cyQ3caTC
4mcq8DcIT8xBBA4+8c5Pp6VsVV1JlFm4aNJdxVFWRcqWLALkemSKYiz2CqN73cIHLOcyL9MD5v59
eucUAWppo7eMySusaDqznAH41U8PXkek6hc3sQ32N1PtkdWGAOP3hJP3Vbfn2YnoBVpHiuolZWSa
MnIZSGGQev4EfpUlAHYUVyHg/WG/tW80pkZVjDSIrOW2KNgAHYKQwIUfdwfUY6+gAooooAKKKKAC
iiigAooooAKKKKACiisq88SWlrI0UQkvJVOHS3AOwjggsSFBB/hznnpQBq0Vhf8ACVr/ANA29/OL
/wCOUf8ACVr/ANA29/OL/wCOUAZlVNU/49k/67w/+jFq3VTVP+PZP+u8P/oxaALdVr6Z44QkZ2zS
t5aHHQnkn8ACcd8YqzVS1/0qc3X8G0xxD2zy30bAx7AHuRQA7T7GPTbOO2iLMiZwXPPJJ/rVmiig
DKsdOhf7T5m8v58hePeQvJ3AEDhsqR1z1x2wNKGGO3jEcSLGg6KgwB+FV7P95cXc/UF/LRv9lRgj
8GL/AP6sVboAKytWt4luLeVwXaaSODy3YeWwyx+YHg8Eke4XHvq1nXUaXerW0TSMBChmaNXwGO5d
hI7gEH6ED15AL6IsaqqqFVRgKowAPSq1x+5v7WQf8tN0LDpngsCfXG0j/gR/G3VbUInms5BGN0q4
dF9WUhlB9sgUAWaKZDMtxCksZ3I6hlOOoPIp9ABVW5tHmuIpUnMO1WQ7VBOCVPGeB930PWrVR3E6
2tvLMwJWNS5C9cAZoAi06Z7jT7WWQ7neJWY46kgE1ZqCxga1sbeFiC0caoSvTIAFT0AUtWYrZghS
5E0RCrjJ/eLxzSPqTxtGrWNwDI21eY+Tgn+/6A0/VP8Aj2T/AK7w/wDoxaL3/j5sP+u5/wDRb0AH
22b/AJ8Lj/vqP/4uoJriSa8sA1rLCPOJ3SFCP9W/HDGtKql7/wAfNh/13P8A6LegC3VTSf8AkF2h
7tErMfUkZJPuSSat1laXqVsumWiCUSSLCgaOEGRh8o6hckUAcF4g/Z08L+ItcvdUluNStpryVppI
7eZNm9uWI3Ix5OT178YGBXdWej2Wi2enaNp1slpZQjekcfRVRgevdixUknk5Yk5q7/aIbiK3uJW/
u+UU/HL4H65pbON2aW4lQxySHARiCVQZwODjuT/wLHaqcm9GddbF18RCNOrNtLYtUUVVfUItzJFm
5lU4McOCQfQnOF79SOlScglj80l5IPuPOdp9dqqp/VSPwrnI/wDilfGUwk407XXUxFfljguFXkMO
mZOoI5JGMHrXQaWzn7WrJ5YWc4TOdu5VY5PrlifxwOKi8SaPBr2g3thcuI4poyPMbohHKt1HQgHG
e1b0ZqLcZfC9H/n8t/wO7CVo05uFX4Jq0vS97+qaT87W2ZxX7QGv/wDCP/Dm8aPel1fMLCKRFBwH
BMgbPYxq478lT2yOJ/Zbtzp+k67qEzqLe6njt48ZLb4lLEYx1ImXAGSdrccc+ffF/wAY6l448TWe
ksn2iXS82KrbfvPtFwW2ySJhAfnKqAvP3eOtfT3gXwnB4O8L6XpqxRi4t7dUmkjZnBkPzSFS3O0u
WbHA56CrnH2cOXqfSYun/ZmVrDSs51Hd27L/AIZfezSdpNVt2VFEVrKuDI3LOpH8IHTIPBPPqtTL
p9sIZYmhWRJl2yiX5zIuMYYnO4YOOe1N0v5bFI+0TNCv0Rioz74Aq3XKfHXtqjlfDbaFceE72Pwy
oayXzUIRHBMhXJzvG5jgrzz2HauoR1kVWVgysMhlOQR61zXgfwW3gmG+to79ruzml82KJ4grRHGD
lgfmJAXsB8vTmtLTdPWSxiEk07tGPKO2VkA2naQAuMjIOCefWqla+h2450niZujNzi3o3u/W6Wp4
r+1hbytb+GZxE5gRrlHlCnarMIioJ6AkK2B32n0rtvgt46tvFXgfTrO1QRahp0KWUsMjhsBEUCXA
52sMYHHIYdAWrpfFHg218SaTe6XJEv2O+iEc53lXVlbckgIHzMDz83XAzxnPyz4f1LVPgj8Syl4q
77VxBexw4kEsDbWJXkcldrLnHIGe4raP7yHL1R9Hg4QzTLvqcdKlO7Xmm/8Ag2+7ufXkPmabCkLo
00CKFSSNCWUDgBl6k9OQPXgYryj9oTwJceLPD663aWaxXeko7ymSRFeS3xuboDnbjcMsOr4BJGfX
dO1CDVtPtb61k821uYlmikwRuRgCpweRkEdasVjGTi7nzWFxFTBV41o7x/po+fP2c/ilaWtnF4S1
SXyJPNY6fM+AjbjkwnjhixYgnOd23jCg/QdfNvxY+A9ydRvtW8KWYlthIfP02HAaL92HLRDPIJJ+
Qcg4Cgg4VPhf+0ZcaX/xL/Fss19a/IsN+qBpYuikSYwXXHzbuXyD97IxvKKn70D6bG4CGZReOy/V
vWUeqf8AX+aufQumTKWu4VO7yZ2ywHB3Hdj6gsRj296vVk+GL60vtLDWNzb3dqjtHHLasHQgHg7l
JDE9SR3JHUGtauY+OacXZlQ/6RqIH8Fuu7/gbAj8wueP9se1W6zZJG0u6i3OHt7qYqS4+dXb7uCB
yvGOeRxzjppUCKs9q/mia3YJLnLq2dsgxjBHY9PmwTx3HFZmoeKIbWX7OoMVxj5mnQ7UOCcEDk9u
nHOcmt2svVNDHiC/sLUFkZvMzJt3Ki7epGQeoUA9MnnqAQDY+Hd8L7T71mfdKbjeyl1ZgDGgBO0D
0PbsR1BrrK4zTtFj8A2sF/LI8iMghvfLJ2AlsrIAeTtJC8ckHOByD2dABRRRQAUUUUAFFFFABRRR
QAUUUUAVtShmuNPuord/KnkiZI5MkbWIIByORzXBaTDqOm3U2naiI/MRTKsnmbnlDO2W9wTnrg9M
jmvRqyvEelvqWnu1uMXsPzwN0yQQSh5HDYwcnHQ9hQBgTTJAFLtjcdqjqWPYAdSfYc1aXR9WZQwt
7VAedslwwYexwhGfoSPeq2jXKza5A8yeTbw20lxulYLscEKwYdioZgc8cn0qa8+JmkWd1JCFuLgI
cebCqlG+hLDP1oA3P+Eb0n/oF2X/AIDp/hR/wjek/wDQLsv/AAHT/CtGigDLk8MaXJjbaLb/APXq
zQ5+uwjP4+9RJ4R0yNVVY51VRgKt3MAB6ferZooAyP8AhFdO/u3H/gXN/wDF0f8ACK6d/duP/Aub
/wCLrXooAxf+ERsEQiA3Fu+ch0uHbBJyThyVOeeo7+tM/wCETX/oJXv5Rf8Axut2igDC/wCETX/o
JXv5Rf8AxumHwfG0yynUb3eqlQf3XQ4J/wCWfsK6CigDC/4RNf8AoJXv5Rf/ABuoW8M3gYhNRh2d
vMtSWx7kOAT9APoK6OigDh7O3eySSzlIMls7RHaMDb1Tuf4Cp6nrzzmmf2vY/wDP7b/9/V/xrrrj
RdOvJmlnsLWaVuskkKsx4xySKu0AcJ/a9j/z+2//AH9X/GquqapZSaZdqt3AzNC4CrIpJO08da9F
ooA4RdVs3YKl1DI54CRuGZj6ADkn2FTee3/Pre/+Acv/AMTXa0UAcDfNJNCqpaXpIljb/jzl6B1J
/h9AaLppJJrRltL0iOUs3+hy8DYw/u+pFd9RQBxXnt/z63v/AIBy/wDxNMlsr+7ktZYdOuHjjkL7
m2RkjYy/ddgw5PcCu4ooA4y4s9Va3lEOmTpMVIRmkhwGxwfv+tLDp99bwpFHpNwqIoVR5kXAHA/5
aV2VFAHKro+rMoYW9qgPO2S4YMPY4QjP0JHvVC6XULe8a0eO2jkEayGRZGkABLAcbVz909x179K7
muW1r/kYpv8Ar1h/9DloAzf7OSXm5drknqrHEf02dCM+uT78VY/d28P8McSL9FUD+Qqv9v8AO4tI
/tP/AE0ztj/7679/ug89cUqWKsyyTsbiQHI3fdU/7K9BjseT70AVLO5kmuL37NGGVpgRM5wn+rQc
DqfXsCO9cj8YPFy+BPB894t7EdcmISxSddw37huZI+nyKSQzZwdoJOQD3Fx/otylz0jZfLmPoBkq
x9gSR/wLJ6V8nfF7xVcfEz4jLY6a32m1hlXT7CNZBslctguDuK/O54YYyoTPStaceaWp7uTYJYzE
rn+COr/y+f5XOp/Zh8E/btWu/E9wv7mxzbWvPWZl+duG/hRsYIIPmccrX0nXO+EdHtvB/huw0LTw
bv7HH5buuQpkyS7MSTty5JKgkjdwMVr/AGWW4/4+nVk6iGMFV+jHPzDt0APOR0wpy5pXOfM8Y8di
pVumy9F/V/mM0uaORbkROskSzttdTnO4BzyPdiPwq9VWS2lWZpbeVIi4G9ZIywJHQjBHOOD9B6Ux
7i8hVnkt4BGo3MVuDnA69VA/Mj61meUcnJ4Z1Kz+K0es2cbHTbq22XkjOmAwUgKAfmxlIjx3zzji
uu0/5Wu4h92Oc49fmAc/qx/DFcX8UPGN/oPh+0n095dPu5bhR+9iViY9jE9QQOdvHWurg1K0kvJL
lLqF7eSBNsyyAodrHPIOP40/76rSV2k2evjPbVqFDEVLWtyK2/u9/PWy8kaleEftU6DFJo+i62Ni
TwzmzfEY3SK6l1y3XClGwP8Apoenf2z7bJNxb20j/wC3KDEo9jkbvyUj9ceafH7wnqXiD4fzTQyJ
cS2E4vZUyY1EKRuG2qSQWG7dzzgEDsCU3aSDKKvscdSle2tvv0Nf4D3kl58KdCaWZp5EWWIl3LFQ
srhV9gFCgDsAK7xpo0kSNnVXfO1SeWx1wO9fPH7OPjq2umHhLVYopWAZ9NZrcMcfM8kbN+bDI/vD
P3RXvsmk23kypDDFbyOpUSRxgFT1B49CAfwoqJxkwzbDzw+NqKatdtr0b0/ruRXFqZdYRkmliYwE
N5bDAww2kgjHOX6+hx0rzv4ifAvT/GVx9tj2afqDBt02n26qJGLhi0iM4Dn7/wAwYNlhncBgei2X
n/2pd+f5efKi2+XnkZfk56HOeO3HXrWjUqTi7o4cPia2Fn7SjKzPjj/itfgTrX8WnNdL/sy290iN
+IyPwcB+27n2/wAC/HjSPFVr5N7eW+hX6b3f+0ZF8sqGG3a/yKThvY/KeD1r0XxLp1prGh3djfW0
d5bXKiFoZQdpLEBSccjDEHI5GMjkCvFNf/Zbs/tktxp+vSWlnJKix20tr5rR7mCkb94yASccZxgZ
PWtuaE/i0Z9PLHYDNIf7cvZ1F9pLf8/x+T6HpsnjLw39pinXxjo8jxqyr9ouoGxnHI2suDx+ta9h
4gi1Cze8sr+w1ezjbbLNZSgiPGC3QsCQDnGQfrmvFv8Ahk3/AKmr/wAp3/22uJ8RfAPxh4QtTqa/
ZbuK1R7mWexudrW6xjduO8Ic9SNuT8v0yuSD2kZQy3La75KOK97zVvzsfWMl4v2hbaDbcXjNgW6u
oc8ZPU8YUE84/Wqug3k8niuzaeC3Bfzbcxs++S3dAxbHOMnAy2OmB3yfm74a/tJa34R1KNdYUarp
kjjz/LjRJ9uAow2MEKMkLxk8bgK+yrH7PPGL2CHy2ukR2Z4TFIwx8u9WAYEA9GGR04rOUHDc8jHZ
biMvklWWj2a2ZBq95ZwxxWl5lkvW+z7Vz0YY5xyBkhcjoWFc54b1Oy8P61c+HxeebBvBtmdtxVyP
njJ4AOeQAOpIznitHxl4WbxRb2iRukUsUuTI+eIyPmwB1PC9fTqKsQ+D9IjsbW0azSWO3fzFMnLF
u5Y984GQeOBxgCoPLNqiiigAooooAKKKKACiiigAooooAKKKKAMXVvCOna1cefPG6SttErQuV81Q
c7X9RwPfgc8Vp2dnBp9rHbW0awwRjaqL2/z61PRQAUUUUAFFFFABRRRQAUUUUAFFFFABRRRQAUUU
UAFFFFABRRRQAUUUUAFFFFABRRRQAVyHiGzguvEUnnwRzbbWLHmIGx88vrXX1y2tf8jFN/16w/8A
octAEFMmmjt4zJK6xoOrOcAfjRNMsMZdzhR7Z+gA7n2qGGF5ZBNMMMPuR9dnufVvft0HckA83+OX
jxfC3hGWIF47/UleCyi2twOA8rEEbSqt8o6hipIODt4P9mv4fQXks/iXUYn3RkxWCMWQNwVlkxgB
xzs4JHLgjpXGfEHUr34sfFqS0sNkwacadZGM+ZGIkYjzNyLkoTvkJ5wCeSBX1Ppnh238O+H7DTdN
jxHp6KIQQoLkDBLYAG58tk46sTXRL93C3Vn2OK/4Ssujho/xKusvTt+n3muiLGqqqhVUYCqMAD0p
1MhmW4hSWM7kdQynHUHkU+uc+OCqkn+nTGMc2y5Eno7f3fcDnPvgf3hTriZ2kSCI4kblmAz5a8/N
9SRgZ+uDg1NDEsEYRBhR+P1JPc+9AGd4iv49LsPtkgY/ZyZvkAJ2qjM+M9ygcD3I6dRT0vWLTxHZ
aZrltC0cUjtHumUBwuWTBwT/ABgdPX3NWtcs4taibS5C/lzIwn2DGI2R1ByRjO7BHuM44p/h/wAP
23h3Q4dKgMk1tEGA8/DMwZixBwAP4j2qtLeZ1r2H1d3v7TmXpy2d/nexp0VU3SWP+sfzLbpvOd0f
+8c8j36jvnkiW6u4bKEyzyLEg7sevfA9T7VJyHyT8XvCtx8M/iMt9pq/ZrWaVdQsJFjGyJw2SgG0
L8jjhRnClM9a+q9N1201PRbDVA/2e2vYI54/tBCsA6hgDzjOD2NeZftF+G18UeBY9VsVS7uNJmMj
NEzMRCwxIAFyDg+WxJ6KhOfXK/Zi8SQ6lpN5o08UIu9NxJbyF8yNE7OWAU9ArE5I/wCeig+/RL34
KXY+wxjeYZXTxO8qekvTv+X3s9f0FoWtWKP5spY7pH/1jLuOwt3+7jGe1aM0ywxl3OFHtn6ADufa
mXFrFdbTIuWX7rqSrL64Ycj8KrPp88k0btclvJBMbMOSxxywGAcDI+jHoRk858eTQwvLIJphhh9y
Prs9z6t79ug7kzTRLcQvFINyOpVh6g8GmW9x525WXy5U++mc49CD3B7H+RBASe+gt2CPIPMIyI1+
ZyPUKOT+XagCMSS2kkaSt50TttEzYDAnoGAAGM8AjuQMd6zfHPhtfF/hHVtHKoz3UDLF5jMqrKPm
jYlecBwp79Oh6VZ1B7yazkZLRQFxIqvL8+VIYDaoIPI6A8+1WmuDcny7ZwcgFplwQoIyMdixHT06
nsC9tS6c5U5qcd1qeJeEf2aNNOk3MOv3L3F8zD/SNPkKrFgn5ELLhuPvFl6nAwVJb3fTdUXQLuOO
QiLSpRt4X5YJM8HOflVsnPGAQDxkmmQxLBGEQYUfj9ST3PvSuiyKysoZWGCrDII9KcpOW51YrGV8
ZLmryv8Apft9xuWsjWGsy2s128kdynm2yTFSdwZjIqkDOACmAc8dOAca1cFeLqjWYit74M0Uwmgk
nDGSM9xvzyMFhhgeDity58VN9jK21q7agePKkBESH+8XwAyjrgcn0HOJOI6GiuRj8QXul3Pn3kv2
uwf/AFu2MBoD/eUDkp6g5IAzk811kciTRrJGyvGwDKynIIPQg0AOooooAKKKKACiiigAooooAKKK
KACiiigAooooAKKKKACiiigAooooAKKKKACiiigAooooAKKKKACiiigAooooAKKKKACiiigArkPE
Mzx+IpFjiaV2tYsAcKPnl5J7D8z6A4rr6+WvGX7VdqfEGpHRNG+2W4iFvbXlxOUDldxEhj252kt9
3cCQBnaTgXGLlsd+EwOIx0nGhG9t+n5ntkNmFkEszefOOjsoGz1CjsP19ScV5t+0N42/4RfwS+nw
Ni+1jdbLx92EAea3KkHghMZB/eZH3a8dvvjp4+8YXgstNk+zyTxNELTSbXc78MWZSdzhsZ5UjG3I
x1qK3+Evj7xnLb3+sx3iW+xg15q0+6WKNdxI8tm8zrnAwASwPAOa2jT5XeTPpsLk0cFVjXx9SKS1
tfV9v+GV77Hffsw+B7izhu/FNz8kd3EbW0VXB3IH/eMwxx8yKBz2bI6Gve6zNO0VtN0+1soLlre3
tYlghjgQbVRQAo+fcScDrmrH9mRN/rHmlJ+9vmfa3rlc7ce2Me1YylzO581j8XLHYiVeXXb06BH/
AKLetH0iny6egf8AiH4/ex67zUl1O0YVIwGmkOFU9hkZY+wBz27DqRULaPZEqVtkiZTkND+7YcY6
rg96TT4hDcXiZYkOu3zGLNs2DHJ5xu3/AI5qDzy1BAtupAJZics7dWPqf8+3SpKKKAOQ+Kml3Gp+
Db1bSKSe5GwCKGMuzqZEJAA+gP8AwH61s+EUaPwnoqOpR1soQVYYIPlrwayPEvjObR/F2g6NawLd
tesTcR7W3xxkgK6kcYGHJ4PC9utampfatKs3lhuY4raHLhWiLMeeI+v3cnHAGABVu6ikz1azq0sF
TozjaMm5p9f5dvkbNZcNtFHrDR72IiiSSGIudqZLq2F9On0zgYGBV77VGtss8p8hCoY+d8u3PY+h
rE1jzLrUrR45GhSNQ0E0eDvLMqk5z0G5eMc8j3qDyjS1bQbDXrWW3v7VLiKWNonzkEqwIIyOejH6
detfKXgfULj4SfGL7FcSbbdLptOuZLgCAPAzgCU7s7V4STryB1wc19V295d2+4ahHGq9RNb5KD2b
PIx1z09xXzn+094ctrHxJpmuW7gtqsLCVVyQWiCAPnPdWQYAA+TPOa3pPVxfU+qyCpGdSeCqfDUT
+9f8C/4H07RXNfDfxI3i7wLo2qyM7zzQBZnkVVLSoSkjYXgAsrEY7EcDpXS1i1Z2PmalOVGcqct0
7fcUtSgYxNNEXWRQNwj+86A5K/XGcdwTwRk1PaxQxQjyAuxvm3Lzuz/ET3J9e9TVU0/92s8HaGUq
v0IDAAdgAwH4UjMt1S09Fsw1ntCCMkxADG5Cc5/AnB78AnrV2q17E7RiSIZnj+ZO271XPocY56cH
sKALNFMhmWaMOhyp9sfUEdj7U+gAooooAKi09Lu31W0ttOlkiikIeWHK+SsasN5CkEgndj5cZJye
malogmexvo7tE80ojRtHnBZWKk4/2vlGM8dRxnIAOwoqK2uI7y3inibfFKgdGwRlSMg81LQAUUUU
AFFFFABRRRQAUUUUAFFFFABRRRQAUUUUAFFFFABRRRQAUUUUAFFFFABRRRQAUUUUAFFFFABRRRQA
UUUUAFFFFAHhf7TXxivfA1jbeH9Em+z6rqELSzXS7hJbwZ2gocY3OQ43A5UIeASrDmP2ZfgnHPY3
PiXxPpMFza3kKx6faX0SSqyE7mmKMpxnChGyCQXOMFSfN5rqb9oT45QRyzSW9lf3PlxK7FWhs41L
bVHzhXKKxwMrvYngGvt61tYbG1htraGO3t4UEccMShURQMBVA4AAGMCumX7uKit2fZ42f9k4KGDp
q1SavJ9f66fLzMLxDaw2Nno9tbQx29vDOI44YlCoiiGQBVA4AAGMCsbV/wDkE3v/AFwf/wBBNb3i
qbdDa2Y6zSiRh3CIQ2Qf97yx9GP1GHqMT3Gn3UUY3O8TKo9SQQK5j43fVlmimQzLcQpLGdyOoZTj
qDyKfQIrajM9vp91LGdrpEzKcdCASKhW1u7e4eZJEutyqm2b5DgEnO5QQfvH+EdvTm66LIrKyhlY
YKsMgj0qvpbtJptsXYtJ5ahyxydwGCD75zmgBPtky/6yymAH3mQoy+5HO4j8M+1SW17DdmQRsd0Z
AdWUqy5GRkEA1PWVrzT2sH2y3kRJI1MYEg4+dlGckgDGO/FAFTVr7UtU0m7XRkmtbkqPs93IiFSw
OfuufukYGcH7x44qt4K1LUvEWgmPXLJre6hfy3kVwvmsrfewpyjAjkYAPBHBwOjs4fs1pDD08tFT
rnoMdcDP5VyPxGsdcP8AZWoaA0z3NvcKstrExVZlJG3fhhlQRgj0djwATVx1909TCcuIX1SXLHmd
1J7rTa/Z6LW6W/mdPHpNvHIsjB55EJKNPI0m3Jzxk8dBz14pP7Ht/LlXMn7xHjyXJ2q3UKOgA4xg
dhTrO+eZYluYGtLh13eUx3DpnG4cEjnI9j1HNLdXEzSCG0RXk3ASSP8AcjHXnnk47D1BOOMweZto
SWM7XNnDK4AkZRvUdm7j8DkfhXk/x3+Geo+NG0KbSoIjFbzSi7BlWIqr7CZPm442HJ68rwe3rdvA
tvEEUk8klm6kk5J/Ek0y+ga6sbiFSA0kbIC3TJBFVGTi+ZHVhMVPB1o16e67+ljh/CGst4P0HStL
1HRn0vTooY4YtQhdZIGOADJLtA8vexByRyXOcYJrv6z3sLLWNF+xzW4kspIxG0EnUAdjzkMCPXII
9RWD4fu28Lanb+F7t5J42Rn067YMfMjGSYnPTcg9ONu3heAelqNaLlBWkt10t3/zO2ooY6MqtONq
iu2lezW7krtu66rtqrJM66qUW5tVnYABVjVH3H5iQSVIH935mGfUe3N2qmpfu4RcD5WhYMX9EyN/
1G3PHsO4Fch45bopqOsiqysGVhkMpyCPWnUAVD/odyD0gmbGOyOcnP0bgfXHUsat0yaJbiF4pBuR
1KsPUHg1V029F4soDGVY22rNtIEg9QcYPOQcemeMigC7RRRQAU10WRWVlDKwwVYZBHpTqZNMtvC8
sh2oilmOOgHJoA6DwxIkvhzTGRldfs0a5U55CgEfgQR+FadZPhVHXQLR3Chpg0+FOcB2LgZx6MK1
qACiiigAooooAKKKKACiiigAooooAKKKKACiiigAooooAKKKKACiiigAooooAKKKKACiiigAoooo
AKKKKACiiigArwv44ftHSfDzW10HQbSC81WHa95Jeo5iiDKGVFCspZiGVic4AwOSTt90r4X+LU2p
aD8dNQ1LxHpv2xV1FbuO2uFUR3dojgRLkAqVMaBCcHkENyCK2pRUnqfR5FhKWKxEvbK6irpd3/X6
Gn+yvpurXXxWtLyxjnOnWsMo1CWNisYRo2CK/POZApC8nK5x8pI+1a5j4b+PLL4k+EbPXLNPI83K
TWzSK7QSqcMhI/AjIBKspwM4rp6mpJylqjlzbFzxmKcqkORx0tvt5nP+JrhJpra0UZmjcXDN/cXD
KMepPI78buh2ms+tDxZsibTZiQrmcwbif4WRjj8WRPy96z6zPGKmkf8AIJsv+uCf+girdVNJ4022
Q/ejQRsPRl+Vh+YNW6ACqmnfKtxEfvRzvn0+Y7x+jD8c1brFvLeJZNRneJDcQslyrFRu2KqnAPbJ
RhQBtVjeKLzybJbfy1P2pvK8yX/Vx+5Pr3H0z2rZrA8Sxi8vNMs5PMMEztuEQG7IAAPPYZOfbNAG
5DH5MKR7mfaoXc5yxx3J9afXOXuoW8msss5tJreMrE0cvzMvq65+UfMwBAJPy5xgUzWrjSo7ptEt
ha2+u3Vs72ivbZXdtbaxO0rgFT19OlNK5rSpTrS5YL/gLq35LqcbdatY+CfFurB9QkvNG1CUNOkc
aTx2tw7sW388MNhwNuSDyGMfPqsMSwRhEGFH4/Uk9z71wOlfDCx0fwjNp+o7bwT/AL26mRQGiYDh
omxnCjPB65bjkqdrTfF9n/wl934XFsto1pEht2VgEkXYrFAuBggMMAZ4UnjFaStL4eh72PjSxkm8
Lecqa952STiuVKVt/Xd21OnooorI+cKj/wCj38ZTn7Rw6em0E7/5KfqvpzDr+gWXiXTJbG+i8yF+
Qw4ZG7Mp7Ef4g5BIpk+o2q6tDm4jJWKVSqsC27cny4HOeDx14qz/AGkjcRw3Ej9l8lkz+LAD8zVR
k4tSi7NGlOpOlNVKbs1szmoddu/BMKWniB5r6yVR5etRQllAxjbMBkq2cANzu3DuDXVfudQtMqyz
W8ycMjZV1YdQR2IPUVXmea8heI2CtE6lXS6dQrAjBGF3ZHrnH41yzeFdX8O3E974ceCGOWQyzaPI
+6B/lPMbbQUYnHHA6c4AFdP7utv7svwf+X5eh6f7jG6yahU+6Mv/AJF/+S/4UdFb79JuoLeS5Mlp
IvlxeYgBRhjC7hwcjPX0rVrjPDviC28aSCB7iaG7t1El1YyqqPFIGxhTt3YBByQcjcucEkV1HnXN
v8rQNdD+GSNlDH/eBIAP0znnp0rnnCVOXLNWZ59ahVw1R0q0bSX9f0+pHePcXUz2ts4hURnzJyu7
axxgDDDDYyfbj1q5DEtvCkUY2oihVHoBwKzbGS7hNyZLKUySzM4ZpI9uMALnByMADOAemeateZff
8+1v/wCBDf8AxFQYFuiqm2+fnzLeH/Y8tpMf8C3Ln8qNPmnm84zPG6K5RGjQrnHDHknvkfh70AW6
gmtkvriztpnZLWabZNtbbldrEKT2DMFX3zjvU9Up1OoOYld0gT70kZ2t5gI27T/skZJ9QB6igDva
KzNF1j+0hLFIuy6t9vmAKQrA5wy57HB47EEc9Tp0AFFFFABRRRQAUUUUAFFFFABRRRQAUUUUAFFF
FABRRRQAUUUUAFFFFABRRRQAUUUUAFFFFABRRRQAUUUUAFFFFABXjP7V1ro7/C2S51CGNtSjuYo9
NmKnesjMC6gjoDGjkg8HaO4WvZq+ZP2yvEv/ACLvh+K5/wCel/cW/l/8Ahfdj/ruMA/UfdrSmrzR
7WTU5VcfSUdLO/3a/jsdP+x7/wAkz1P/ALC8v/omGvdK4D4D+G4fDHwn8PQxeW73Vst/LKkQQu0w
8z5vUqrKm49Qg6dB39KbvJs58yqKtjKs47XZU1bT01bTbmzfaFmjKbmXdtJHDY9jg/hXIXE0mjxx
R6kkscpxH5ixlklb1UqCOSDgHB9hXdU2SNJo2jkRXjYFWVhkEHqCKg8087sdUghVoHEwmLySeX5E
m7aZGIONvTkVb+2zf8+Fx/31H/8AF1oXng9rXVJNQ087w0fl/Y3bAUZyfLPQdBhTgcnkDiq8cnmK
TgqVZkZW6qwJBH4EEcUAV/Mvv+fa3/8AAhv/AIimx2LyNcG6kSYTRrEVjQoNo3f7R/vGrtFAGXJY
ouoQxCS42NFIxH2mTqCgH8XuagvI47G6kZJHeSK2e5jDK87Ky8YJySqMHOTwMopzxitCP/kLXP8A
1wi/9Ckrz3WrXXvFPiuLTIZdQsNDnRbm5uYwU8xFZ/LCkgcEYAHPJLEHHFRV2deFw6xFTllNRSTb
b7L832RPrfjbw7ousR6UkN3qF2kq+d9liWbzZPmGxtzDL5bnAPXHBHG54f8Ah/ZaHr2oaw7/AGu9
uJXaFmTAt4z/AAKMnnHGfQYAHOde30c2M0stq8KSzBRK8luu5gowoym3OBxzn2xVj7TdR/6yz356
fZ5Q357tv6Zp82lonRLFQp0/Z4VOPMrSd7823krK/wB63G6h5rNAqwPNEG3uIyoOV5Uckd8Hj+7j
vWB4ma30EyeJ72xhFzaRLCJ4y0zhGfGFQlFBy5+bOcEjvXRJqUDMqkvGWOF86NowT6AsBk+1Ra7o
tt4i0m5068DG3nXDbGwwIIIIPqCAfTjnNKL11ObDVI06sXUbUW7Stu49V9w2zUapZwXS3001tcRr
KuwCNWVhkEYAYDkcZz60640W3uIXQqXcj5HmZpdh7Ebie+Mjvjmq3hiKw07T10qx1H+0PsH7p986
ySx8nCtjpjBAGBgLjtVq+upWkSC0KvLvUTYwTEh6t6A9MA9fQ0nuZ1oKnUlGN7X0vvbp+BPYyLNZ
wuqCIbR+7H8B6FfwPH4VPWclreWqzLBNHIGYyK847kfdwoAAJ5yPU8HrV23nW6t4plBCyKHAbrgj
NIxJKKKKAOa1zw7Hql7dzWoW11aKKOa1vF+V0k+cAFsHKEAAqcggnjPNGjeOtNurEDUL610/UYWM
N1bTzLGUlXhwMtyuehBPHvmtDQZmvluLx1KPMygKT91AoIGM8ckntnOcc1Rk0TTdW8TXsk+nWdx5
cMaytPbozM55U5IP8PH4D0rpjUi48lW+m39dj0qWIpSp+yxKbS2a3Xlr0626P1Z0dFeVXEfiGGVd
N0fUI7a1jYxRwXUzeZbZYLsDj/WKCRjOSACMYGTtzab4q0NVaDxRZ6i8YLNa6hbrErKcjJYEt94j
HIHv2Newi9VUX4/5aGn1GlLVYiGu1+a/ztFpP1dvNrU6/Vpvs+l3cm/yyIm2tnGDjjB9c4pkN1Hb
wRQJCxmRFBt4jvMfA4LZwOPUjOOK4j/hIfFdxp97JeaXZ3VtCMOLJ3imiYfNvG4/Nt2/dHJJFWdL
1bTvEH2a8guI7G206TFx9snYTF/vFmVjtTdg8A4yG5bFRKjOK5lqvLUwqYKrTjzxtKPeLul69vnv
0Oum87yXlu7mO0t0Us/lnG1QOcyHtjJyACPXiuXs/HF7qW7/AIR7w3cajp6cC6nnW3WQ7mBK7wdw
4yTnOTyAetTV/EU3xEhfRvD0cwspm2XerSIyRIgCllToWY5wVOOM9juHd2dpFYWkFtAnlwQosca5
JwoGAMn2FbckcPH97G8n0fRedrO7O10aeX008TT5qsvsttcq7ySad30V1a12tUcIfiRb2twb2/0/
WNEfZFH55gKhZASxj3fxAgg4I5AyR0r1bwz4lj8QWaMV8qcoJAuPlkQgEOnJyCCO5wTg9ief035o
5pD9955Nx9drFR+igfhXEa54b1vQpri40bZcaPGTcxabE7RywyY58rgjG758e5CgE5MctOtpBcr8
3o/8vn+BkqeGxjcaK9nPonL3X5JtaP1dn3XX3KivMfCvxGN4yWUepQ313GdslnfxNbXK/Kcpnncy
lTnhu+T0rtbXxVZybluz/Z8q8H7QdsZOB91+h6+x4PArnnCVN8s1ZnnVqNXDy5KsXF9mrGzRRRUG
IUUUUAFFFNkkSGNpJGVI1BZmY4AA6kmgB1FYV14ny+LCBbtB96WSQxqf907TuHv05GCecVH1zVJG
LJ9jgU9I2jeUj/gW5c/kP60AdRRRRQAUUUUAFFFFABRRRQAUUUUAFFFFABRRRQAUUUUAFFFFABRR
RQAUUUUAFfFXxG/4ul+0fLpY+3S2bajFphReZIYoyEnKD5gqgrLJnGMEsR1r7B8Ua1/wjfhnV9X8
n7T/AGfZzXfk7tvmbELbc4OM4xnBr5I/ZM8O/wBrfE59SdJ/K0qzkmWSMfuxK+I1VzjujyEDIJKZ
6A10U9E5H1mSf7PRxGNf2Y2Xq/6X3n2XRRRXOfJhRRRQAVgeI7EW4/tCJcYYC4A6MnTfj1XjJ/ug
5zgY36KAPMtU1p31AaXbApOxw0jAkfdyANvPPQntyfcQ6fbyXWt3aSXTzQ20McJZJGQs2Op2nnnf
1Peui1bwdcLbpa2XlXNg05kktpztIG1ETa+Cfl2k5GCRx83fP0vwvrGm3t/LcfYoYHCtJcNIduQC
WcD2ySQdoyeCBQBna5JLZRzw27G+v7mAiOKbHzlc7UwoXAYs2WJGACQcgCk8BWGr2OhE65KZNQmm
eV0IX90OFVBtOMYUEAYABCgACsFPBlxr3jq31q4uRPpNjg24kRo5ZnADeYQAAF3kkHJ+VFUjA49B
q3ZKyPSqyhRoRowak5Wk3bWO/u3/ABdku1woooqDzRrosisrKGVhgqwyCPSqemzLDotm7nCiCPtn
+EYAHc+1SPfB2aO2UTyqcHkhFx1BbBwfbryOMc0yx0xLSOEO5uJIlCJJIB8oAxhQOn8/UnFAHI+H
fC1xa+OvEGoRSSWmm3SofJBOZGb5mJ5+RgQTgjIEvG2uu05Rbm4thnbHISu4ksVYbsknr8xYZ9vX
Ncp468Oaj4o0cDSpFiuU1NJ0ZpChQIpiLAjoQfm45wOOeK6qNpI76F5VWOSeDbIFYsodTkKpIGfv
P25C5wOauWqTPTxc3iKdPETmnJ+611Sikk33v3L1VNN/dxzQ94ZWX2APzKB7BWA/CrdUbiaOxvkm
ldY4pk8tnc4AZSSo/EF/yH4weYXqpavu+wOqgN5jJGVY4BDOFIz2yCRmhb6W4LC3tXIU433GYlPH
bgt39Mdeail+0yXtj5oiQCRm8uMlzgIw3buOMkDp3HPOKAFutOmku5XgmW3SZFWVlT958pPIOeCQ
SMnpgfhz15Y3ej3kl3ZvM1iyZV4mD4+Q7QwPVR684HfNdDr9vNdaa6QvInI8wRKGZk/iAGR25xnn
GO9UbLWLZLVrCPdfPCgVR8v7+P1Ueu3naeex5BoAfp3h9tSt7e/hs3v4p2eRrhWSKXerAKduQEAw
/wB1jknJ7AUtQWXWmihvtMn0pnYLHdSxnG7khCSB154B64ruPBuoS3lj5Rt5oraJE8h5oyhKHOF9
GwAOQejDPOSdXVns49Nna/ZVtFXLsxIxzwRjnOcYxznGOaAPN7NYopvKu0ktLC1lD3l2YZZorpw6
FQwIOwkdSDg59MVRTwPpet3Ey6xo8kU0R3wxySuNkL5ZVBDDODu69898121p4FtbzSZo79JYri6l
E77Zy7RYJCIGPXCsQSc5yfbHP6XqYvPEOs+Zd+fumKwbpN2UDOQF56AHt61cZypvmg7M2pVqtCft
KUnGXdOz/A2YYY7eFIokWKKNQqIgwqgDAAHYUTTLbwvLIdqIpZjjoByafVLWNx02dFALSgQjccAF
yFz+Gagybb1ZJp0T2+n2sUg2ukSqw9CAAas0UUCMjxF4XsvE1vClz5kU0DiSC6t22SwsCDlWxxnA
/IHqARh/8JFq/g+PHiOH7fYB9o1izA+UM2F82IAFcDqVyOVHJ5rs6rXEztIkERxI3LMBny15+b6k
jAz9cHBrohWtHkmrx/L0fT8vI9GjjOWCo1o88O2zXflfT8V1aZmWMWk61IZbNLOe1t32l4Ajh32g
4yOMAMPx9McpNqV7axLLdQX0EIYCST+0pGCKSBnAbJ6njFZt18PUtb0Xnh/UZfD9wQqyRwoJIJAF
IBMZwC3PU/XGTmo7ibxPabbe70Cz8R+X/q7yOdIMr0+ZHBwxxk7eOQB0q3RhPWlJej0f46fiaywd
KtrhaqflJqLXzdov5Sv5G1falc2en/bDDqRgZI5FY6g3R84LASEqDjgkcnjipLbxHrLsI7ZNSknt
mRprOaBD8mCxUuV3DIHBPzHI4JNcPpcPivTZZW/4RnzFkTYyG9tyCMg8h1YdQO1bUHxE1mzZoJtL
8QxLGqoI7XToXRGHDKGC4ZeBggDI7Uvq1TpZ+jT/ACZP9mYl/Dyv0nB/lJnqNtrS/wBjf2hfx/2e
q7i6yZ+UBiB1APOBgYzyK4rxBqWq6hqyXA09pdOtxuit3dQ27HLkBjls5x146DJzXIyeJZtd8Saf
aaha61a6ZcPjzdUBiVp/nIUD7oyOBtwewHevRayqUp0mlNbnLiMLWwrUa0bXV1s/yKsd8WmWKS3l
gZgSu8qc46/dY/n06eoq1Uc9vHcqFlQOAcj1B9Qex9xWWtxqtmPJ+wC8CkgTCcLuGeODzwOOSenU
9ayOU9IooooAKKKKACiiigAooooAKKKKACiiigAooooAKKKKACiiigAooooAKKKKAOA+Pejza58H
/E9tA0aOlsLomQkDbC6ysOAeSqED3I6da8V/Yz1iGHXPE2lMshuLq2hukYAbAsTMrAnOc5mXHHY9
OM/SvibxFZeEfD+oazqD7LOyhaZ8FQzYHCruIBZjhQM8kgd6+Uf2Pf8Akpmp/wDYIl/9HQ10Q/hy
R9bl7c8pxVOS91Wfz0/yR9hUUUVznyQUUUUAFFFFABXK6xqC6xObdN621rN8x5XzZFPT3VT+bD0H
PVVlX3hqxvCzqjWc7NvM1qfLZjnOW7N/wIHqfWgDEqrfSOPIijcxNNJs8xQCVABY8EY5C4/HNa83
hu8hybe7juFH3Y7hNrH6uvH5J7e9YdtN9s1GRyjR/Z1MJVsZDlyHU4JGRsXoeh9xQAs0N7BC7QXP
nvtJCXEanJ7AFduM++aIVmv4UeSVRAyhh5BZWfuDngqP9kc8dTyKvVSjU2uoFNx8m4BdVOAEcYyB
/vAk4/2WPc0AW0RY1VVUKqjAVRgAelOoooAo6fG02kptkaF50MnmIBlGfLEjII4LcZB6c5rjPh/N
ry6Jdwaxb3r6jptyZImvFOJUKkFVfkuR8/PP3k5I4rttN+WGSI8GKV12/wB0ZyoHttK/TpXJ+JPH
n9m+IJ/D9zYeUtxblre7NwuH3KeqkcchwOSSQBj5quN2mkj1ML7SrRq4enTUtFK/Vcu9u+j1R2dv
cR3UKTQuJI3GQwqlqV0iyQlQzvBKrMQPkRT8rFj04Vicdeh6VX0O0nk0m18yZrdCgxFAFUFfUnBO
T1JBHXsa0/skP2ZrcRKsDKVMaDaMHr0+tQeWTVVuY3W4iuEQy7FZDGpAJDFTkZOONv6+2DEmpLba
WJ7liWjDJIwHV1yDjtyVOM46j1qR7yS0jt3v7SXT1nXKvMV2bsZ2kg8Hr94DoaAGyaxbKuUZ5n6e
XChZtx4CkAfKSeMHHNSaD4dtNS09IZIzY6xpsrI0ixqjn+4XVT8ylcc55wcHkk1NRvLK90+6hF1b
uWibA3hsYBOcDJ4xnj0rs9BjibTLW6SPEtxbxNJI+Gkf5Bje2BuI9aAM/wAF+YtnexSW7WhiuSgt
2xiP92hIGOMEknI65z3rYutPt7ya3lnj8xrd/MjDMdobGN2M4JHYnp2qzRQB5n4tt9fv7WW7u9OK
pGHwmYnWCM7fu4JZm+UZY9OcAdQaCL2zvrqy1OLy7wIkgYqNzrjGSw4bHHOe5/DoPEHhNtQvri8e
5t0jfa3nXCbjbKgBwAflKkgk/d6nOa5bw+t9aSXTPAt6ju2bqKVSZSGYEjJ+bJJOTjjueBQB0tVN
Q+f7NF08ydfm9NuX/XZj8akgvYbhiiMRJjPlyKUbHrggHHvVfS0a4UX0yp506grtH3I+oXPfrkn1
PsKALc9xHbKGlcIpOMn/AD6ZPsATWe2pTvDPNGIRHC2AuS7S9CoBGACwK4xu+8PTFTTbrjVoI/mC
W6GZumCzZVffpv8A0pbywMlu4tdkE24yg7RtZ8dWHfnBz6gHnGKALM8626gkFmJwqL1Y+g/z79KZ
ZwNDGTIQZpDvlK9C2AOPYAAD6etVfs/2CS2ZpZJ4gwjzM24oW4DA9yTxznG7jAyDo0AFFMhmjuIx
JE6yIejIcg/jT6ACiimTCRoXETKkpU7GdSyg44JGRke2R9aBo4/xEsuu+PNF0jd5dpYp/a0pDDLs
rFUA+U9G688hj3Ars64rw2sfh+O8vnu5tZmvrhUmuvLCO7hWICp2UAqoGfXGBgV2busaszMFVRks
xwAPWuitNO0I7R/Huz0MZWhLko0neMFa/d7t666vv0S22HVlzeJdNt5nikudroxVhsbgjg9qfruo
S6fZqYImlnmfyYwvUMQcEDBzyOlZVp4Xvbq3jlfw3JLIw+aSa88tmbuSrEEZPNc55x6tRRRQAUUU
UAFFFFABRRRQAUUUUAFFFFABRRRQAUUUUAFFFFABRRRQAUUUUAfNP7ZHitFtdB8NRtGzs7ajOpRt
6AAxxEN93BzNkcn5R079/wDs0+Co/CfwxsbuS38rUdX/ANNndtjMUP8AqQGXnb5e1gpJIMjdM4Hz
d/yXz47f8+drq15/uOtrFH/wMCQxRe43nsK+6K6KnuxUD6/NP9hwNHALd+9L/L77/cgooornPkAo
oooAKKKKACiiigArhrOBYZtQYEky3s7nPr5hXj8AK6rX5Hh0LUZI2ZJFtpGVlOCCFOCDXI6Oirps
BVQiyAyhVGAoYltv4Zx+FAF2q19E8lvmMZljYSIOhJBzjPbIyufQmrNVWvB/aaWgIJMLStwcj5gB
/wCzflQBPDMs0YdDlT7Y+oI7H2p9UtLULHcFc7GnkK7iSfvYb6fMGxjtjvmrtAFS4/0W4imX5Ukc
JL6cjCnHrnaM+h56DEWt26SWE8/lxNNDExR5Iw2ACGI57EovHQ4GQelXLiBbq3lhYkLIpQleuCMV
VSS+F4tmiQ3MjRNJE0kgiMm3GUAwctg5zwOvTFA722GWqppL3Vu0vnIrxvG8MTBZFkVcFFGeC27h
eM5wB0qC88RRWs0W1fMi/eLMPuPGyjIBDYwThuDycceh0fAOladtm/0JJJ4zHPFcTIGYowJQ9Thg
QwOAOgNWPHWkxX1zZGSFSJY5bfzsDKvgOnfPG1/zPrQIxYL6zuLPUrp9s1p5u47l4bEacYbvkfnW
l4S8RCSextbeRpLKYvCsMzfPCUUsNvcrgc5JxlcYxitTT9T0PUItMnmhs4LuTEcEThGdCrMAFI/h
3KcEYHTucVqW2i2tjeLPa29vajy2R1igVS2SpB3AZ4weO+fagCpq/hW01jVLO+l/1kHysrKHWROf
lIYEdT19z3wRtUUUAFFFFAHEeNbOdNasbyWIX9lIDbi38sHy2xuBGWwScHJwMBeanqr4u162bxNZ
afIjyCDnAJ2iZyu0kHA4XnPP3/arVAEc9vHcqFlQOAcj1B9Qex9xVKawntbR1sbiRCiERQttZRxw
MkZ/M4H04rRooArafHFHaRmFmkR1D+Y5JZ8gcknvjFWaqab8lu0HQwO0YX0XOUH/AHyV/wD11JfS
SxWczwANMqllUqWyRzjAPegCjJ9r/tK2+0BPJEzCLyzg52PgnOc/Lx1XnPBGDUuuSKumXEe5xJJG
VVY13Ek8AYweCSBn/aHcis59Vj1TWIY0njFhAomcs+3e2Nw75IHBx2wc9qhtYb++1RZ49ElvC0sk
sNw6mJWUhdh3FcYAQ4yf4vXqAW/DUkFuLiwiniuPJbek0Qx5qMAQSDzuGcEduBUtrYza3r876XMq
PFH5NzNNkrHluAi92+Vj/d496TSPCutQzxOmnW1i8dt5LNJKCsp3E7iVJO7leOmAeRwK7fRNJbSb
eVXn+0SzSmV32bRnAAAHOAAo7mgDmtZsdT8P2P2rMeqQxr+98uMxOvT5+rAjrnAGOvTOJNJsdU1a
BHeD+zRsBL3EZJZuQQI9wIHHUn04PWuyooA4TVhpHhuxntb6ytdS1Jg0qhYSryozElt207Nvzdzw
gORniC18I6rrVrtlll0i1b5gk0pnmb5FGG6YB+YkZHJxtrpNV8NnUtbtr7fEoi8o/NHucbJC+FOe
N2cE9sdDnjeoAzrDw/YafIJo4Fe5zk3MoDSE4wTu7cdhgegrRoooAKKKKACiiigAooooAKKKKACi
iigAooooAKKKKACiiigAooooAKKKKACvNv2hvFaeFPhPrLboxcagn9nQpIjMHMoIccdCIxIwJ4yo
69D6TUV1aw31rNbXMMdxbzIY5IZVDI6kYKsDwQQcYNNOzudGHqRo1oVJq6TTt6Hz5+x74R+x+H9Y
8RzxYlvZhaW7SQYYRRjLsjnqrO2CBxmHuRx9EVV03S7LRbGOz0+0gsLOPOy3toljjXJJOFUADJJP
1NWqqUuZ3N8dinjcROu+v5dAoooqDgCiiigAooooAKKKKACuNaFbW+vraMYihmwg9AyK+PoNxAHY
AV2VcrrChfEFwFG0NbxOcd23SDJ98Ko+gHpQBDWLoNz9rk1O8QGRHmwnTcwVRgdB2xjJ/qTtVznh
fVIY4IdOfKXChvlYHO7cxI6cYAH50AauioRp0UjHLz5nbrgFzuwAScAZq9VK3dYdSubcMAGVZwue
ckkNgemQD9WPrU0F0s09zFwGhYKRnJwVBBx26kfhQBS1qO4aS0e3ZY2icv5jh3XpjaVRSTkE844w
eRmpvDl5Fr2taVPEFEkKSyyKX+ZBjYVwPUsDk44FXqu+D9tutzaMqNNCseJ1jCs8WCsYcjqy7WH0
x70ASaP4WOk6vLdrcq0BSRI7ZItixhpN/rjjpwBwB6VP4pspbrS/NtwzXFq4uEjX+PAIZeh6qWAx
3xWxRQB5nH4ANjphvSXnM8IU2zW5aSDfjkAcsyk88DjJ9q7/AEaa7uNLtpb6NIrqRNzxxggLnkDB
5BxjPvmrtFABRRRQAUUUUAcj4x0tW1fSdQVMuGaBj5hU9Cy9ByAA/HGcjPFNpdfxrGoXNrcDfaWz
KghIGC5TJfOM5xJjGeMZ69EoAKK5vX9QuIdYhgWTFusX2ho9o+YoWfGeozsArIudTktY4URp2VYF
DyBtrB5GEjENjuBjn3/EA6aS50u4vJE88R3ADF/LkaInbkHcQRnGD17c9Kn0+a4fSY5nHnzshkVc
gZzkqCcAZxgZxWL/AGLdf8IfYXBiMt5cXzvGGdlLRtGdwbkfe8vPuD15q/pMJ0W3lgml+1XcjGYR
Q5eV8qM4XqeQefbJxzgAxdC0G4k1i206S08uaQSNNNvJxCwCkjGQCMMAT1LjPavXra3js7eKCJdk
USBEXJOFAwBzWd4f02Szt2nukCXs4HmKrbgignag+mTk+pPbGNagAooooAKKKKACiiigAooooAKK
KKACiiigAooooAKKKKACiiigAooooAKKKKACiiigAooooAKKKKACiiigAooooAKKKKACiiigAooo
oAKKKKACuF8TXUsPjizhRsRTWo3rgc4MhFFFAFque1a7mhvLKFHKxyamWYDuRFCBz9GYfjRRQBrR
/wDIWuf+uEX/AKFJWXYzOvi7UYgfkaJWIx3AUD+ZoooA1o5nbUJoifkWKNgMdyXB/kKs+H7iRfF0
0AbET2IdlwOWWQgH/wAeP50UUAdhRRRQAUUUUAFFFFABRRRQBwdncSXV/rDytuYX0iA4A+VQqgfk
BS6v/wAgm9/64P8A+gmiigDhNYvpzePb+YRDbM8USjjan3cZ6ngY5r1u38F6LazGRbCORtuz98Wl
GOMcMSOwoooAo6Z4R0dtU1KVrCJmiudqK2SgBiRiNudvVm7cdugroLPTbTT9/wBltYbbfjd5MYTd
jpnA9zRRQBZooooAKKKKACiiigAooooAKKKKAP/Z</Data></Thumbnail></Binary><mdContact xmlns=""><rpIndName>Michael Trust</rpIndName><rpOrgName>MassGIS</rpOrgName><rpPosName>Sr. GIS Database Administrator</rpPosName><rpCntInfo xmlns=""><cntAddress addressType="both"><delPoint>One Ashburton Place, 8th Floor</delPoint><city>Boston</city><adminArea>MA</adminArea><postCode>02108</postCode><country>US</country></cntAddress><cntPhone><voiceNum tddtty="">617-619-5615</voiceNum></cntPhone></rpCntInfo><displayName>Michael Trust</displayName><role><RoleCd value="007"/></role></mdContact><mdMaint xmlns=""><maintFreq><MaintFreqCd value="009"/></maintFreq></mdMaint><dqInfo><dataLineage><prcStep xmlns=""><stepDesc>Removed section of rail south of the 'Wickford Junction' stop on the Providence line. Coded the section from 'Fitchburg' to 'Wachusett' as Active.</stepDesc><stepRat>Based on current mbta.com maps and input from RIDOT.</stepRat><stepDateTm>2021-12-23T00:00:00</stepDateTm><stepProc xmlns=""><rpIndName>Michael Trust</rpIndName><rpOrgName>MassGIS</rpOrgName><rpPosName>Sr. GIS Database Administrator</rpPosName><rpCntInfo xmlns=""><cntAddress addressType="both"><delPoint>One Ashburton Place, 8th Floor</delPoint><city>Boston</city><adminArea>MA</adminArea><postCode>02108</postCode><country>US</country></cntAddress><cntPhone><voiceNum tddtty="">617-619-5615</voiceNum></cntPhone></rpCntInfo><displayName>Michael Trust</displayName><role><RoleCd value="007"/></role><displayName>Michael Trust</displayName></stepProc></prcStep><prcStep xmlns=""><stepDesc>Removed the Plymouth spur at the end of the Kingston line.</stepDesc><stepDateTm>2023-11-02T00:00:00</stepDateTm><stepProc xmlns=""><editorSource>external</editorSource><editorDigest>646e9c317dd4cc36398847bd137e04fa</editorDigest><rpOrgName>MassGIS</rpOrgName><rpCntInfo xmlns=""><cntAddress addressType="both"><delPoint>1 Ashburton place, 8th Floor</delPoint><city>Boston</city><adminArea>MA</adminArea><postCode>02108</postCode><eMailAdd>massgismail@mass.gov</eMailAdd></cntAddress></rpCntInfo><editorSave>True</editorSave><displayName>MassGIS</displayName><role><RoleCd value="005"></RoleCd></role></stepProc></prcStep></dataLineage></dqInfo></metadata>
